{
  "description": "sample Github_easy/o43982.json",
  "meta": {
    "full_size": 381,
    "stripped_size": 289,
    "features": [
      "additionalProperties"
    ],
    "raw_features": [
      "$schema",
      "_boolSchema",
      "properties",
      "required",
      "type",
      "type:integer",
      "type:object",
      "type:string"
    ]
  },
  "schema": {
    "$schema": "http://json-schema.org/draft-04/schema#",
    "additionalProperties": false,
    "properties": {
      "location": {
        "_format": "uri",
        "type": "string"
      },
      "retries": {
        "type": "integer"
      },
      "retryInterval": {
        "type": "integer"
      },
      "startTime": {
        "_format": "date-time",
        "type": "string"
      },
      "stopTime": {
        "_format": "date-time",
        "type": "string"
      }
    },
    "required": [
      "location"
    ],
    "title": "GetDiagnosticsRequest",
    "type": "object"
  },
  "tests": [
    {
      "description": "llama 70b generated valid",
      "valid": true,
      "data": {
        "location": "https://example.com/diagnostics",
        "retries": 3,
        "retryInterval": 300,
        "startTime": "2022-01-01T12:00:00Z",
        "stopTime": "2022-01-01T13:00:00Z"
      }
    },
    {
      "description": "llama-70b generated negative",
      "valid": false,
      "rust_error": "Additional properties are not allowed ('extraProperty' was unexpected)",
      "python_error": "Additional properties are not allowed ('extraProperty' was unexpected)\n\nFailed validating 'additionalProperties' in schema:\n    {'$schema': 'http://json-schema.org/draft-04/schema#',\n     'additionalProperties': False,\n     'properties': {'location': {'_format': 'uri', 'type': 'string'},\n                    'retries': {'type': 'integer'},\n                    'retryInterval': {'type': 'integer'},\n                    'startTime': {'_format': 'date-time', 'type': 'string'},\n                    'stopTime': {'_format': 'date-time', 'type': 'string'}},\n     'required': ['location'],\n     'title': 'GetDiagnosticsRequest',\n     'type': 'object'}\n\nOn instance:\n    {'location': 'https://example.com/diagnostics',\n     'retries': 3,\n     'retryInterval': 300,\n     'startTime': '2022-01-01T12:00:00Z',\n     'stopTime': '2022-01-01T13:00:00Z',\n     'extraProperty': 'value'}",
      "data": {
        "location": "https://example.com/diagnostics",
        "retries": 3,
        "retryInterval": 300,
        "startTime": "2022-01-01T12:00:00Z",
        "stopTime": "2022-01-01T13:00:00Z",
        "extraProperty": "value"
      }
    },
    {
      "description": "llama-70b generated negative",
      "valid": false,
      "rust_error": "Additional properties are not allowed ('extraProperty' was unexpected)",
      "python_error": "Additional properties are not allowed ('extraProperty' was unexpected)\n\nFailed validating 'additionalProperties' in schema:\n    {'$schema': 'http://json-schema.org/draft-04/schema#',\n     'additionalProperties': False,\n     'properties': {'location': {'_format': 'uri', 'type': 'string'},\n                    'retries': {'type': 'integer'},\n                    'retryInterval': {'type': 'integer'},\n                    'startTime': {'_format': 'date-time', 'type': 'string'},\n                    'stopTime': {'_format': 'date-time', 'type': 'string'}},\n     'required': ['location'],\n     'title': 'GetDiagnosticsRequest',\n     'type': 'object'}\n\nOn instance:\n    {'location': 'https://example.com/diagnostics',\n     'retries': 3,\n     'retryInterval': 300,\n     'startTime': '2022-01-01T12:00:00Z',\n     'stopTime': '2022-01-01T13:00:00Z',\n     'extraProperty': 'extraValue'}",
      "data": {
        "location": "https://example.com/diagnostics",
        "retries": 3,
        "retryInterval": 300,
        "startTime": "2022-01-01T12:00:00Z",
        "stopTime": "2022-01-01T13:00:00Z",
        "extraProperty": "extraValue"
      }
    },
    {
      "description": "llama 70b generated positive",
      "valid": true,
      "data": {
        "location": "https://example.com/diagnostics",
        "retries": 3,
        "retryInterval": 300,
        "startTime": "2022-01-01T00:00:00Z",
        "stopTime": "2022-01-01T01:00:00Z"
      }
    }
  ]
}