{
  "description": "sample Github_easy/o91027.json",
  "meta": {
    "full_size": 478,
    "stripped_size": 300,
    "features": [
      "additionalProperties"
    ],
    "raw_features": [
      "$schema",
      "_boolSchema",
      "id",
      "properties",
      "type",
      "type:integer",
      "type:object",
      "type:string"
    ]
  },
  "schema": {
    "$schema": "http://json-schema.org/draft-04/schema#",
    "type": "object",
    "title": "Zenodo SIPStore Agent GitHub Client Schema v1.0.0.",
    "description": "User agent information making the SIP.",
    "id": "http://zenodo.org/schemas/sipstore/agent-githubclient-v1.0.0.json",
    "additionalProperties": false,
    "properties": {
      "$schema": {
        "type": "string"
      },
      "user_id": {
        "description": "Zenodo User ID",
        "type": "integer"
      },
      "github_id": {
        "description": "GitHub user ID",
        "type": "integer"
      },
      "email": {
        "type": "string"
      }
    }
  },
  "tests": [
    {
      "description": "llama 70b generated valid",
      "valid": true,
      "data": {
        "$schema": "http://json-schema.org/draft-04/schema#",
        "user_id": 12345,
        "github_id": 67890,
        "email": "user@example.com"
      }
    },
    {
      "description": "llama-70b generated negative",
      "valid": false,
      "rust_error": "Additional properties are not allowed ('extra_property' was unexpected)",
      "python_error": "Additional properties are not allowed ('extra_property' was unexpected)\n\nFailed validating 'additionalProperties' in schema:\n    {'$schema': 'http://json-schema.org/draft-04/schema#',\n     'type': 'object',\n     'title': 'Zenodo SIPStore Agent GitHub Client Schema v1.0.0.',\n     'description': 'User agent information making the SIP.',\n     'id': 'http://zenodo.org/schemas/sipstore/agent-githubclient-v1.0.0.json',\n     'additionalProperties': False,\n     'properties': {'$schema': {'type': 'string'},\n                    'user_id': {'description': 'Zenodo User ID',\n                                'type': 'integer'},\n                    'github_id': {'description': 'GitHub user ID',\n                                  'type': 'integer'},\n                    'email': {'type': 'string'}}}\n\nOn instance:\n    {'$schema': 'http://json-schema.org/draft-04/schema#',\n     'user_id': 12345,\n     'github_id': 67890,\n     'email': 'user@example.com',\n     'extra_property': 'extra_value'}",
      "data": {
        "$schema": "http://json-schema.org/draft-04/schema#",
        "user_id": 12345,
        "github_id": 67890,
        "email": "user@example.com",
        "extra_property": "extra_value"
      }
    },
    {
      "description": "llama 70b generated positive",
      "valid": true,
      "data": {
        "$schema": "http://zenodo.org/schemas/sipstore/agent-githubclient-v1.0.0.json",
        "user_id": 12345,
        "github_id": 67890,
        "email": "user@example.com"
      }
    },
    {
      "description": "llama-70b generated negative",
      "valid": false,
      "rust_error": "Additional properties are not allowed ('extra_property' was unexpected)",
      "python_error": "Additional properties are not allowed ('extra_property' was unexpected)\n\nFailed validating 'additionalProperties' in schema:\n    {'$schema': 'http://json-schema.org/draft-04/schema#',\n     'type': 'object',\n     'title': 'Zenodo SIPStore Agent GitHub Client Schema v1.0.0.',\n     'description': 'User agent information making the SIP.',\n     'id': 'http://zenodo.org/schemas/sipstore/agent-githubclient-v1.0.0.json',\n     'additionalProperties': False,\n     'properties': {'$schema': {'type': 'string'},\n                    'user_id': {'description': 'Zenodo User ID',\n                                'type': 'integer'},\n                    'github_id': {'description': 'GitHub user ID',\n                                  'type': 'integer'},\n                    'email': {'type': 'string'}}}\n\nOn instance:\n    {'$schema': 'http://zenodo.org/schemas/sipstore/agent-githubclient-v1.0.0.json',\n     'user_id': 12345,\n     'github_id': 67890,\n     'email': 'user@example.com',\n     'extra_property': 'extra_value'}",
      "data": {
        "$schema": "http://zenodo.org/schemas/sipstore/agent-githubclient-v1.0.0.json",
        "user_id": 12345,
        "github_id": 67890,
        "email": "user@example.com",
        "extra_property": "extra_value"
      }
    }
  ]
}