{
  "description": "sample Github_easy/o45307.json",
  "meta": {
    "full_size": 391,
    "stripped_size": 391,
    "features": [
      "additionalProperties",
      "items",
      "pattern"
    ],
    "raw_features": [
      "_boolSchema",
      "properties",
      "required",
      "type",
      "type:array",
      "type:boolean",
      "type:number",
      "type:object",
      "type:string"
    ]
  },
  "schema": {
    "additionalProperties": false,
    "properties": {
      "exclude": {
        "items": {
          "type": "string"
        },
        "type": "array"
      },
      "name": {
        "type": "string"
      },
      "port": {
        "type": "number"
      },
      "readable": {
        "type": "boolean"
      },
      "ssh": {
        "pattern": "^.+@.+$",
        "type": "string"
      },
      "url": {
        "pattern": "^https?://",
        "type": "string"
      },
      "vagrant": {
        "type": "string"
      },
      "writable": {
        "type": "boolean"
      }
    },
    "required": [
      "name",
      "url",
      "readable",
      "writable"
    ],
    "type": "object"
  },
  "tests": [
    {
      "description": "llama 70b generated valid",
      "valid": true,
      "data": {
        "name": "example",
        "port": 8080,
        "readable": true,
        "ssh": "user@example.com",
        "url": "https://",
        "vagrant": "example",
        "writable": false
      }
    },
    {
      "description": "llama-70b generated negative; focus on pattern keyword",
      "valid": false,
      "rust_error": "\"invalid\" does not match \"^.+@.+$\"",
      "python_error": "'ftp://' does not match '^https?://'\n\nFailed validating 'pattern' in schema['properties']['url']:\n    {'pattern': '^https?://', 'type': 'string'}\n\nOn instance['url']:\n    'ftp://'",
      "data": {
        "name": "example",
        "port": 8080,
        "readable": true,
        "ssh": "invalid",
        "url": "ftp://",
        "vagrant": "example",
        "writable": false
      }
    },
    {
      "description": "llama-70b generated negative",
      "valid": false,
      "rust_error": "\"ftp://\" does not match \"^https?://\"",
      "python_error": "Additional properties are not allowed ('extraProperty' was unexpected)\n\nFailed validating 'additionalProperties' in schema:\n    {'additionalProperties': False,\n     'properties': {'exclude': {'items': {'type': 'string'},\n                                'type': 'array'},\n                    'name': {'type': 'string'},\n                    'port': {'type': 'number'},\n                    'readable': {'type': 'boolean'},\n                    'ssh': {'pattern': '^.+@.+$', 'type': 'string'},\n                    'url': {'pattern': '^https?://', 'type': 'string'},\n                    'vagrant': {'type': 'string'},\n                    'writable': {'type': 'boolean'}},\n     'required': ['name', 'url', 'readable', 'writable'],\n     'type': 'object'}\n\nOn instance:\n    {'name': 'example',\n     'port': 8080,\n     'readable': True,\n     'ssh': 'user@example.com',\n     'url': 'ftp://',\n     'vagrant': 'example',\n     'writable': False,\n     'extraProperty': 'extraValue'}",
      "data": {
        "name": "example",
        "port": 8080,
        "readable": true,
        "ssh": "user@example.com",
        "url": "ftp://",
        "vagrant": "example",
        "writable": false,
        "extraProperty": "extraValue"
      }
    },
    {
      "description": "llama-70b generated negative; focus on pattern keyword",
      "valid": false,
      "rust_error": "\"invalid\" does not match \"^.+@.+$\"",
      "python_error": "'invalid' does not match '^.+@.+$'\n\nFailed validating 'pattern' in schema['properties']['ssh']:\n    {'pattern': '^.+@.+$', 'type': 'string'}\n\nOn instance['ssh']:\n    'invalid'",
      "data": {
        "name": "example",
        "port": 8080,
        "readable": true,
        "ssh": "invalid",
        "url": "https://",
        "vagrant": "example",
        "writable": false
      }
    },
    {
      "description": "llama-70b generated negative",
      "valid": false,
      "rust_error": "\"ftp://\" does not match \"^https?://\"",
      "python_error": "Additional properties are not allowed ('extraProperty' was unexpected)\n\nFailed validating 'additionalProperties' in schema:\n    {'additionalProperties': False,\n     'properties': {'exclude': {'items': {'type': 'string'},\n                                'type': 'array'},\n                    'name': {'type': 'string'},\n                    'port': {'type': 'number'},\n                    'readable': {'type': 'boolean'},\n                    'ssh': {'pattern': '^.+@.+$', 'type': 'string'},\n                    'url': {'pattern': '^https?://', 'type': 'string'},\n                    'vagrant': {'type': 'string'},\n                    'writable': {'type': 'boolean'}},\n     'required': ['name', 'url', 'readable', 'writable'],\n     'type': 'object'}\n\nOn instance:\n    {'name': 'example',\n     'port': 8080,\n     'readable': True,\n     'ssh': 'user@example.com',\n     'url': 'ftp://',\n     'writable': False,\n     'extraProperty': 'extraValue'}",
      "data": {
        "name": "example",
        "port": 8080,
        "readable": true,
        "ssh": "user@example.com",
        "url": "ftp://",
        "writable": false,
        "extraProperty": "extraValue"
      }
    },
    {
      "description": "llama 70b generated positive",
      "valid": true,
      "data": {
        "exclude": [
          "path1",
          "path2"
        ],
        "name": "example",
        "port": 8080,
        "readable": true,
        "ssh": "user@example.com",
        "url": "https://example.com",
        "vagrant": "vagrant@example.com",
        "writable": false
      }
    },
    {
      "description": "llama-70b generated negative; focus on pattern keyword",
      "valid": false,
      "rust_error": "\"ftp://example.com\" does not match \"^https?://\"",
      "python_error": "'ftp://example.com' does not match '^https?://'\n\nFailed validating 'pattern' in schema['properties']['url']:\n    {'pattern': '^https?://', 'type': 'string'}\n\nOn instance['url']:\n    'ftp://example.com'",
      "data": {
        "exclude": [
          "path1",
          "path2"
        ],
        "name": "example",
        "port": 8080,
        "readable": true,
        "ssh": "user@example.com",
        "url": "ftp://example.com",
        "vagrant": "vagrant@example.com",
        "writable": false
      }
    },
    {
      "description": "llama-70b generated negative",
      "valid": false,
      "rust_error": "123 is not of type \"string\"",
      "python_error": "Additional properties are not allowed ('extra' was unexpected)\n\nFailed validating 'additionalProperties' in schema:\n    {'additionalProperties': False,\n     'properties': {'exclude': {'items': {'type': 'string'},\n                                'type': 'array'},\n                    'name': {'type': 'string'},\n                    'port': {'type': 'number'},\n                    'readable': {'type': 'boolean'},\n                    'ssh': {'pattern': '^.+@.+$', 'type': 'string'},\n                    'url': {'pattern': '^https?://', 'type': 'string'},\n                    'vagrant': {'type': 'string'},\n                    'writable': {'type': 'boolean'}},\n     'required': ['name', 'url', 'readable', 'writable'],\n     'type': 'object'}\n\nOn instance:\n    {'name': 'example',\n     'url': 'https://example.com',\n     'readable': True,\n     'writable': False,\n     'port': 8080,\n     'ssh': 'user@example.com',\n     'vagrant': 'vagrant@example.com',\n     'exclude': ['path1', 'path2', 123],\n     'extra': 'invalid key'}",
      "data": {
        "name": "example",
        "url": "https://example.com",
        "readable": true,
        "writable": false,
        "port": 8080,
        "ssh": "user@example.com",
        "vagrant": "vagrant@example.com",
        "exclude": [
          "path1",
          "path2",
          123
        ],
        "extra": "invalid key"
      }
    }
  ]
}