{
  "description": "sample Github_easy/o81565.json",
  "meta": {
    "full_size": 407,
    "stripped_size": 407,
    "features": [
      "additionalProperties",
      "dependencies"
    ],
    "raw_features": [
      "$schema",
      "_boolSchema",
      "properties",
      "required",
      "type",
      "type:object",
      "type:string"
    ]
  },
  "schema": {
    "$schema": "http://json-schema.org/draft-04/schema#",
    "type": "object",
    "properties": {
      "businessName": {
        "type": "string"
      },
      "contactName": {
        "type": "string"
      },
      "line1": {
        "type": "string"
      },
      "city": {
        "type": "string"
      },
      "state": {
        "type": "string"
      },
      "zip": {
        "type": "string"
      },
      "country": {
        "type": "string"
      }
    },
    "additionalProperties": false,
    "required": [
      "line1",
      "city",
      "state",
      "zip",
      "country"
    ],
    "dependencies": {
      "businessName": [
        "contactName"
      ]
    }
  },
  "tests": [
    {
      "description": "llama 70b generated positive",
      "valid": true,
      "data": {
        "businessName": "ABC Corporation",
        "contactName": "John Doe",
        "line1": "123 Main St",
        "city": "Anytown",
        "state": "CA",
        "zip": "12345",
        "country": "USA"
      }
    },
    {
      "description": "llama 70b generated positive",
      "valid": true,
      "data": {
        "businessName": "ABC Corporation",
        "contactName": "John Doe",
        "line1": "123 Main St",
        "city": "New York",
        "state": "NY",
        "zip": "10001",
        "country": "USA"
      }
    },
    {
      "description": "llama-70b generated negative; focus on dependencies keyword",
      "valid": false,
      "rust_error": "\"contactName\" is a required property",
      "python_error": "'contactName' is a dependency of 'businessName'\n\nFailed validating 'dependencies' in schema:\n    {'$schema': 'http://json-schema.org/draft-04/schema#',\n     'type': 'object',\n     'properties': {'businessName': {'type': 'string'},\n                    'contactName': {'type': 'string'},\n                    'line1': {'type': 'string'},\n                    'city': {'type': 'string'},\n                    'state': {'type': 'string'},\n                    'zip': {'type': 'string'},\n                    'country': {'type': 'string'}},\n     'additionalProperties': False,\n     'required': ['line1', 'city', 'state', 'zip', 'country'],\n     'dependencies': {'businessName': ['contactName']}}\n\nOn instance:\n    {'businessName': 'ABC Corporation',\n     'line1': '123 Main St',\n     'city': 'New York',\n     'state': 'NY',\n     'zip': '10001',\n     'country': 'USA'}",
      "data": {
        "businessName": "ABC Corporation",
        "line1": "123 Main St",
        "city": "New York",
        "state": "NY",
        "zip": "10001",
        "country": "USA"
      }
    },
    {
      "description": "llama-70b generated negative",
      "valid": false,
      "rust_error": "\"contactName\" is a required property",
      "python_error": "'contactName' is a dependency of 'businessName'\n\nFailed validating 'dependencies' in schema:\n    {'$schema': 'http://json-schema.org/draft-04/schema#',\n     'type': 'object',\n     'properties': {'businessName': {'type': 'string'},\n                    'contactName': {'type': 'string'},\n                    'line1': {'type': 'string'},\n                    'city': {'type': 'string'},\n                    'state': {'type': 'string'},\n                    'zip': {'type': 'string'},\n                    'country': {'type': 'string'}},\n     'additionalProperties': False,\n     'required': ['line1', 'city', 'state', 'zip', 'country'],\n     'dependencies': {'businessName': ['contactName']}}\n\nOn instance:\n    {'businessName': 'ABC Corporation',\n     'line1': '123 Main St',\n     'city': 'New York',\n     'state': 'NY',\n     'zip': '10001',\n     'country': 'USA'}",
      "data": {
        "businessName": "ABC Corporation",
        "line1": "123 Main St",
        "city": "New York",
        "state": "NY",
        "zip": "10001",
        "country": "USA"
      }
    }
  ]
}