{
  "description": "sample Github_easy/o27395.json",
  "meta": {
    "full_size": 289,
    "stripped_size": 236,
    "features": [
      "additionalProperties"
    ],
    "raw_features": [
      "$schema",
      "_boolSchema",
      "properties",
      "required",
      "type",
      "type:integer",
      "type:object",
      "type:string"
    ]
  },
  "schema": {
    "$schema": "http://json-schema.org/draft-04/schema#",
    "type": "object",
    "title": "image",
    "description": "Image representation",
    "properties": {
      "id": {
        "type": "string"
      },
      "name": {
        "type": "string"
      },
      "width": {
        "type": "integer"
      },
      "height": {
        "type": "integer"
      }
    },
    "required": [
      "name"
    ],
    "additionalProperties": false
  },
  "tests": [
    {
      "description": "llama 70b generated valid",
      "valid": true,
      "data": {
        "id": "image-123",
        "name": "Example Image",
        "width": 800,
        "height": 600
      }
    },
    {
      "description": "llama-70b generated negative",
      "valid": false,
      "rust_error": "Additional properties are not allowed ('extraProperty' was unexpected)",
      "python_error": "Additional properties are not allowed ('extraProperty' was unexpected)\n\nFailed validating 'additionalProperties' in schema:\n    {'$schema': 'http://json-schema.org/draft-04/schema#',\n     'type': 'object',\n     'title': 'image',\n     'description': 'Image representation',\n     'properties': {'id': {'type': 'string'},\n                    'name': {'type': 'string'},\n                    'width': {'type': 'integer'},\n                    'height': {'type': 'integer'}},\n     'required': ['name'],\n     'additionalProperties': False}\n\nOn instance:\n    {'id': 'image-123',\n     'name': 'Example Image',\n     'width': 800,\n     'height': 600,\n     'extraProperty': 'Invalid'}",
      "data": {
        "id": "image-123",
        "name": "Example Image",
        "width": 800,
        "height": 600,
        "extraProperty": "Invalid"
      }
    },
    {
      "description": "llama-70b generated negative",
      "valid": false,
      "rust_error": "Additional properties are not allowed ('unknownProperty' was unexpected)",
      "python_error": "Additional properties are not allowed ('unknownProperty' was unexpected)\n\nFailed validating 'additionalProperties' in schema:\n    {'$schema': 'http://json-schema.org/draft-04/schema#',\n     'type': 'object',\n     'title': 'image',\n     'description': 'Image representation',\n     'properties': {'id': {'type': 'string'},\n                    'name': {'type': 'string'},\n                    'width': {'type': 'integer'},\n                    'height': {'type': 'integer'}},\n     'required': ['name'],\n     'additionalProperties': False}\n\nOn instance:\n    {'id': 'image-123',\n     'name': 'Example Image',\n     'width': 800,\n     'height': 600,\n     'unknownProperty': 'value'}",
      "data": {
        "id": "image-123",
        "name": "Example Image",
        "width": 800,
        "height": 600,
        "unknownProperty": "value"
      }
    }
  ]
}