{
  "description": "sample Github_easy/o53024.json",
  "meta": {
    "full_size": 437,
    "stripped_size": 409,
    "features": [
      "additionalProperties"
    ],
    "raw_features": [
      "$schema",
      "_boolSchema",
      "properties",
      "required",
      "type",
      "type:object",
      "type:string"
    ]
  },
  "schema": {
    "$schema": "http://json-schema.org/draft-04/schema#",
    "title": "Thing data upload",
    "type": "object",
    "properties": {
      "thing": {
        "type": "object",
        "properties": {
          "id": {
            "type": "string"
          },
          "title": {
            "type": "string"
          },
          "description": {
            "type": "string"
          },
          "license": {
            "type": "string"
          },
          "license_url": {
            "type": "string"
          }
        },
        "additionalProperties": false,
        "required": [
          "id",
          "title",
          "description",
          "license",
          "license_url"
        ]
      }
    },
    "additionalProperties": false,
    "required": [
      "thing"
    ]
  },
  "tests": [
    {
      "description": "llama 70b generated valid",
      "valid": true,
      "data": {
        "thing": {
          "id": "example-id",
          "title": "Example Title",
          "description": "This is an example description.",
          "license": "MIT License",
          "license_url": "https://opensource.org/licenses/MIT"
        }
      }
    },
    {
      "description": "llama-70b generated negative",
      "valid": false,
      "rust_error": "Additional properties are not allowed ('extra_property' was unexpected)",
      "python_error": "Additional properties are not allowed ('extra_property' was unexpected)\n\nFailed validating 'additionalProperties' in schema['properties']['thing']:\n    {'type': 'object',\n     'properties': {'id': {'type': 'string'},\n                    'title': {'type': 'string'},\n                    'description': {'type': 'string'},\n                    'license': {'type': 'string'},\n                    'license_url': {'type': 'string'}},\n     'additionalProperties': False,\n     'required': ['id', 'title', 'description', 'license', 'license_url']}\n\nOn instance['thing']:\n    {'id': 'example-id',\n     'title': 'Example Title',\n     'description': 'This is an example description.',\n     'license': 'MIT License',\n     'license_url': 'https://opensource.org/licenses/MIT',\n     'extra_property': 'This is an extra property'}",
      "data": {
        "thing": {
          "id": "example-id",
          "title": "Example Title",
          "description": "This is an example description.",
          "license": "MIT License",
          "license_url": "https://opensource.org/licenses/MIT",
          "extra_property": "This is an extra property"
        }
      }
    },
    {
      "description": "llama 70b generated positive",
      "valid": true,
      "data": {
        "thing": {
          "id": "example-thing-id",
          "title": "Example Thing Title",
          "description": "This is an example thing description.",
          "license": "MIT License",
          "license_url": "https://opensource.org/licenses/MIT"
        }
      }
    },
    {
      "description": "llama-70b generated negative",
      "valid": false,
      "rust_error": "Additional properties are not allowed ('extra_property' was unexpected)",
      "python_error": "Additional properties are not allowed ('extra_property' was unexpected)\n\nFailed validating 'additionalProperties' in schema['properties']['thing']:\n    {'type': 'object',\n     'properties': {'id': {'type': 'string'},\n                    'title': {'type': 'string'},\n                    'description': {'type': 'string'},\n                    'license': {'type': 'string'},\n                    'license_url': {'type': 'string'}},\n     'additionalProperties': False,\n     'required': ['id', 'title', 'description', 'license', 'license_url']}\n\nOn instance['thing']:\n    {'id': 'example-thing-id',\n     'title': 'Example Thing Title',\n     'description': 'This is an example thing description.',\n     'license': 'MIT License',\n     'license_url': 'https://opensource.org/licenses/MIT',\n     'extra_property': 'This property is not allowed'}",
      "data": {
        "thing": {
          "id": "example-thing-id",
          "title": "Example Thing Title",
          "description": "This is an example thing description.",
          "license": "MIT License",
          "license_url": "https://opensource.org/licenses/MIT",
          "extra_property": "This property is not allowed"
        }
      }
    }
  ]
}