{
  "description": "sample Github_easy/o12069.json",
  "meta": {
    "full_size": 412,
    "stripped_size": 315,
    "features": [
      "additionalProperties",
      "items",
      "pattern"
    ],
    "raw_features": [
      "_boolSchema",
      "properties",
      "required",
      "type",
      "type:array",
      "type:object",
      "type:string"
    ]
  },
  "schema": {
    "additionalProperties": false,
    "items": {
      "additionalProperties": false,
      "properties": {
        "brand": {
          "type": "string"
        },
        "description": {
          "type": "string"
        },
        "id": {
          "pattern": "^[\\d]+$",
          "type": "string"
        },
        "image": {
          "type": "string"
        },
        "name": {
          "type": "string"
        }
      },
      "required": [
        "id",
        "brand",
        "name",
        "description"
      ],
      "type": "object"
    },
    "self": {
      "format": "jsonschema",
      "name": "product/items",
      "vendor": "com.nordstrom",
      "version": "1-0-0"
    },
    "type": "array"
  },
  "tests": [
    {
      "description": "llama 70b generated valid",
      "valid": true,
      "data": [
        {
          "brand": "Nike",
          "description": "This is a high-quality running shoe.",
          "id": "12345",
          "image": "https://example.com/image.jpg",
          "name": "Nike Air Max"
        },
        {
          "brand": "Adidas",
          "description": "This is a lightweight and comfortable shoe.",
          "id": "67890",
          "image": "https://example.com/image2.jpg",
          "name": "Adidas Superstar"
        }
      ]
    },
    {
      "description": "llama-70b generated negative; focus on pattern keyword",
      "valid": false,
      "rust_error": "False schema does not allow false",
      "python_error": "Additional properties are not allowed ('additionalProperties', 'items', 'self', 'type' were unexpected)\n\nFailed validating 'additionalProperties' in schema:\n    {'additionalProperties': False,\n     'items': {'additionalProperties': False,\n               'properties': {'brand': {'type': 'string'},\n                              'description': {'type': 'string'},\n                              'id': {'pattern': '^[\\\\d]+$',\n                                     'type': 'string'},\n                              'image': {'type': 'string'},\n                              'name': {'type': 'string'}},\n               'required': ['id', 'brand', 'name', 'description'],\n               'type': 'object'},\n     'self': {'format': 'jsonschema',\n              'name': 'product/items',\n              'vendor': 'com.nordstrom',\n              'version': '1-0-0'},\n     'type': 'array'}\n\nOn instance:\n    {'additionalProperties': False,\n     'items': {'additionalProperties': False,\n               'properties': {'brand': {'type': 'string.. (578 more)",
      "data": {
        "additionalProperties": false,
        "items": {
          "additionalProperties": false,
          "properties": {
            "brand": {
              "type": "string"
            },
            "description": {
              "type": "string"
            },
            "id": {
              "pattern": "^[\\d]+$",
              "type": "string"
            },
            "image": {
              "type": "string"
            },
            "name": {
              "type": "string"
            }
          },
          "required": [
            "id",
            "brand",
            "name",
            "description"
          ],
          "type": "object"
        },
        "self": {
          "format": "jsonschema",
          "name": "product/items",
          "vendor": "com.nordstrom",
          "version": "1-0-0"
        },
        "type": "array"
      }
    },
    {
      "description": "llama-70b generated negative",
      "valid": false,
      "rust_error": "False schema does not allow \"Nike\"",
      "python_error": "Additional properties are not allowed ('brand', 'description', 'id', 'image', 'name', 'price' were unexpected)\n\nFailed validating 'additionalProperties' in schema:\n    {'additionalProperties': False,\n     'items': {'additionalProperties': False,\n               'properties': {'brand': {'type': 'string'},\n                              'description': {'type': 'string'},\n                              'id': {'pattern': '^[\\\\d]+$',\n                                     'type': 'string'},\n                              'image': {'type': 'string'},\n                              'name': {'type': 'string'}},\n               'required': ['id', 'brand', 'name', 'description'],\n               'type': 'object'},\n     'self': {'format': 'jsonschema',\n              'name': 'product/items',\n              'vendor': 'com.nordstrom',\n              'version': '1-0-0'},\n     'type': 'array'}\n\nOn instance:\n    {'brand': 'Nike',\n     'description': 'This is a high-quality running shoe.',\n     'id': '12345',\n     'image': 'https://example.com/image.jpg',\n     'name': 'Nike Air Max',\n     'price': '100'}",
      "data": {
        "brand": "Nike",
        "description": "This is a high-quality running shoe.",
        "id": "12345",
        "image": "https://example.com/image.jpg",
        "name": "Nike Air Max",
        "price": "100"
      }
    },
    {
      "description": "llama-70b generated negative; focus on pattern keyword",
      "valid": false,
      "rust_error": "False schema does not allow \"Nike\"",
      "python_error": "Additional properties are not allowed ('brand', 'description', 'id', 'image', 'name' were unexpected)\n\nFailed validating 'additionalProperties' in schema:\n    {'additionalProperties': False,\n     'items': {'additionalProperties': False,\n               'properties': {'brand': {'type': 'string'},\n                              'description': {'type': 'string'},\n                              'id': {'pattern': '^[\\\\d]+$',\n                                     'type': 'string'},\n                              'image': {'type': 'string'},\n                              'name': {'type': 'string'}},\n               'required': ['id', 'brand', 'name', 'description'],\n               'type': 'object'},\n     'self': {'format': 'jsonschema',\n              'name': 'product/items',\n              'vendor': 'com.nordstrom',\n              'version': '1-0-0'},\n     'type': 'array'}\n\nOn instance:\n    {'brand': 'Nike',\n     'description': 'This is a high-quality running shoe.',\n     'id': '123abc',\n     'image': 'https://example.com/image.jpg',\n     'name': 'Nike Air Max'}",
      "data": {
        "brand": "Nike",
        "description": "This is a high-quality running shoe.",
        "id": "123abc",
        "image": "https://example.com/image.jpg",
        "name": "Nike Air Max"
      }
    }
  ]
}