{
  "description": "sample Github_easy/o5140.json",
  "meta": {
    "full_size": 511,
    "stripped_size": 282,
    "features": [
      "additionalProperties",
      "additionalProperties:object"
    ],
    "raw_features": [
      "$id",
      "$schema",
      "_boolSchema",
      "properties",
      "type",
      "type:object",
      "type:string"
    ]
  },
  "schema": {
    "$schema": "http://json-schema.org/draft-07/schema#",
    "$id": "https://github.com/Enfernuz/quik-lua-rpc/json/schema/GetLabelParams.result.scheme.json",
    "title": "Результат процедуры GetLabelParams",
    "description": "Схема объекта результата удалённого вызова процедуры GetLabelParams",
    "type": "object",
    "properties": {
      "label_params": {
        "description": "Результат",
        "type": "object",
        "additionalProperties": {
          "type": "string"
        }
      }
    },
    "additionalProperties": false
  },
  "tests": [
    {
      "description": "llama 70b generated valid",
      "valid": true,
      "data": {
        "label_params": {
          "key1": "value1",
          "key2": "value2",
          "key3": "value3"
        }
      }
    },
    {
      "description": "llama-70b generated negative; focus on additionalProperties keyword with an object schema",
      "valid": false,
      "rust_error": "123 is not of type \"string\"",
      "python_error": "123 is not of type 'string'\n\nFailed validating 'type' in schema['properties']['label_params']['additionalProperties']:\n    {'type': 'string'}\n\nOn instance['label_params']['key3']:\n    123",
      "data": {
        "label_params": {
          "key1": "value1",
          "key2": "value2",
          "key3": 123
        }
      }
    },
    {
      "description": "llama-70b generated negative",
      "valid": false,
      "rust_error": "123 is not of type \"string\"",
      "python_error": "Additional properties are not allowed ('extra_key' was unexpected)\n\nFailed validating 'additionalProperties' in schema:\n    {'$schema': 'http://json-schema.org/draft-07/schema#',\n     '$id': 'https://github.com/Enfernuz/quik-lua-rpc/json/schema/GetLabelParams.result.scheme.json',\n     'title': 'Результат процедуры GetLabelParams',\n     'description': 'Схема объекта результата удалённого вызова процедуры '\n                    'GetLabelParams',\n     'type': 'object',\n     'properties': {'label_params': {'description': 'Результат',\n                                     'type': 'object',\n                                     'additionalProperties': {'type': 'string'}}},\n     'additionalProperties': False}\n\nOn instance:\n    {'label_params': {'key1': 'value1', 'key2': 'value2', 'key3': 123},\n     'extra_key': 'extra_value'}",
      "data": {
        "label_params": {
          "key1": "value1",
          "key2": "value2",
          "key3": 123
        },
        "extra_key": "extra_value"
      }
    },
    {
      "description": "llama-70b generated negative; focus on additionalProperties keyword with an object schema",
      "valid": false,
      "rust_error": "Additional properties are not allowed ('extra_key' was unexpected)",
      "python_error": "Additional properties are not allowed ('extra_key' was unexpected)\n\nFailed validating 'additionalProperties' in schema:\n    {'$schema': 'http://json-schema.org/draft-07/schema#',\n     '$id': 'https://github.com/Enfernuz/quik-lua-rpc/json/schema/GetLabelParams.result.scheme.json',\n     'title': 'Результат процедуры GetLabelParams',\n     'description': 'Схема объекта результата удалённого вызова процедуры '\n                    'GetLabelParams',\n     'type': 'object',\n     'properties': {'label_params': {'description': 'Результат',\n                                     'type': 'object',\n                                     'additionalProperties': {'type': 'string'}}},\n     'additionalProperties': False}\n\nOn instance:\n    {'label_params': {'key1': 'value1', 'key2': 'value2', 'key3': 'value3'},\n     'extra_key': 'extra_value'}",
      "data": {
        "label_params": {
          "key1": "value1",
          "key2": "value2",
          "key3": "value3"
        },
        "extra_key": "extra_value"
      }
    },
    {
      "description": "llama-70b generated negative",
      "valid": false,
      "rust_error": "123 is not of type \"string\"",
      "python_error": "123 is not of type 'string'\n\nFailed validating 'type' in schema['properties']['label_params']['additionalProperties']:\n    {'type': 'string'}\n\nOn instance['label_params']['key2']:\n    123",
      "data": {
        "label_params": {
          "key1": "value1",
          "key2": 123,
          "key3": "value3"
        }
      }
    },
    {
      "description": "llama 70b generated positive",
      "valid": true,
      "data": {
        "label_params": {
          "param1": "value1",
          "param2": "value2",
          "param3": "value3"
        }
      }
    },
    {
      "description": "llama-70b generated negative; focus on additionalProperties keyword with an object schema",
      "valid": false,
      "rust_error": "{\"nestedParam\":\"nestedValue\"} is not of type \"string\"",
      "python_error": "Additional properties are not allowed ('extraParam' was unexpected)\n\nFailed validating 'additionalProperties' in schema:\n    {'$schema': 'http://json-schema.org/draft-07/schema#',\n     '$id': 'https://github.com/Enfernuz/quik-lua-rpc/json/schema/GetLabelParams.result.scheme.json',\n     'title': 'Результат процедуры GetLabelParams',\n     'description': 'Схема объекта результата удалённого вызова процедуры '\n                    'GetLabelParams',\n     'type': 'object',\n     'properties': {'label_params': {'description': 'Результат',\n                                     'type': 'object',\n                                     'additionalProperties': {'type': 'string'}}},\n     'additionalProperties': False}\n\nOn instance:\n    {'label_params': {'param1': 'value1',\n                      'param2': 'value2',\n                      'param3': 'value3',\n                      'param4': {'nestedParam': 'nestedValue'}},\n     'extraParam': 'extraValue'}",
      "data": {
        "label_params": {
          "param1": "value1",
          "param2": "value2",
          "param3": "value3",
          "param4": {
            "nestedParam": "nestedValue"
          }
        },
        "extraParam": "extraValue"
      }
    },
    {
      "description": "llama-70b generated negative",
      "valid": false,
      "rust_error": "null is not of type \"string\"",
      "python_error": "None is not of type 'string'\n\nFailed validating 'type' in schema['properties']['label_params']['additionalProperties']:\n    {'type': 'string'}\n\nOn instance['label_params']['param2']:\n    None",
      "data": {
        "label_params": {
          "param1": "value1",
          "param2": null,
          "param3": "value3"
        }
      }
    }
  ]
}