{
  "description": "sample Github_easy/o41735.json",
  "meta": {
    "full_size": 419,
    "stripped_size": 257,
    "features": [
      "additionalProperties"
    ],
    "raw_features": [
      "$schema",
      "_boolSchema",
      "properties",
      "type",
      "type:[]",
      "type:null",
      "type:object",
      "type:string"
    ]
  },
  "schema": {
    "$schema": "http://json-schema.org/draft-04/schema#",
    "title": "UiModuleDescriptor",
    "description": "UI Module description",
    "type": [
      "object",
      "null"
    ],
    "additionalProperties": false,
    "properties": {
      "npm": {
        "description": "NPM module",
        "type": [
          "string",
          "null"
        ]
      },
      "url": {
        "description": "URL",
        "type": [
          "string",
          "null"
        ]
      },
      "local": {
        "description": "Local",
        "type": [
          "string",
          "null"
        ]
      },
      "args": {
        "description": "Arguments",
        "type": [
          "string",
          "null"
        ]
      }
    }
  },
  "tests": [
    {
      "description": "llama 70b generated valid",
      "valid": true,
      "data": {
        "npm": "module-name",
        "url": "https://example.com/module",
        "local": "/path/to/local/module",
        "args": "--arg1 --arg2"
      }
    },
    {
      "description": "llama-70b generated negative; focus on type keyword with an array of types",
      "valid": false,
      "rust_error": "Additional properties are not allowed ('extra' was unexpected)",
      "python_error": "Additional properties are not allowed ('extra' was unexpected)\n\nFailed validating 'additionalProperties' in schema:\n    {'$schema': 'http://json-schema.org/draft-04/schema#',\n     'title': 'UiModuleDescriptor',\n     'description': 'UI Module description',\n     'type': ['object', 'null'],\n     'additionalProperties': False,\n     'properties': {'npm': {'description': 'NPM module',\n                            'type': ['string', 'null']},\n                    'url': {'description': 'URL',\n                            'type': ['string', 'null']},\n                    'local': {'description': 'Local',\n                              'type': ['string', 'null']},\n                    'args': {'description': 'Arguments',\n                             'type': ['string', 'null']}}}\n\nOn instance:\n    {'npm': 'module-name',\n     'url': 'https://example.com/module',\n     'local': '/path/to/local/module',\n     'args': '--arg1 --arg2',\n     'extra': 'extra-value'}",
      "data": {
        "npm": "module-name",
        "url": "https://example.com/module",
        "local": "/path/to/local/module",
        "args": "--arg1 --arg2",
        "extra": "extra-value"
      }
    },
    {
      "description": "llama-70b generated negative",
      "valid": false,
      "rust_error": "Additional properties are not allowed ('extra' was unexpected)",
      "python_error": "Additional properties are not allowed ('extra' was unexpected)\n\nFailed validating 'additionalProperties' in schema:\n    {'$schema': 'http://json-schema.org/draft-04/schema#',\n     'title': 'UiModuleDescriptor',\n     'description': 'UI Module description',\n     'type': ['object', 'null'],\n     'additionalProperties': False,\n     'properties': {'npm': {'description': 'NPM module',\n                            'type': ['string', 'null']},\n                    'url': {'description': 'URL',\n                            'type': ['string', 'null']},\n                    'local': {'description': 'Local',\n                              'type': ['string', 'null']},\n                    'args': {'description': 'Arguments',\n                             'type': ['string', 'null']}}}\n\nOn instance:\n    {'npm': 'module-name',\n     'url': 'https://example.com/module',\n     'local': '/path/to/local/module',\n     'args': '--arg1 --arg2',\n     'extra': 'extra property'}",
      "data": {
        "npm": "module-name",
        "url": "https://example.com/module",
        "local": "/path/to/local/module",
        "args": "--arg1 --arg2",
        "extra": "extra property"
      }
    },
    {
      "description": "llama-70b generated negative; focus on type keyword with an array of types",
      "valid": false,
      "rust_error": "123 is not of types \"null\", \"string\"",
      "python_error": "123 is not of type 'string', 'null'\n\nFailed validating 'type' in schema['properties']['npm']:\n    {'description': 'NPM module', 'type': ['string', 'null']}\n\nOn instance['npm']:\n    123",
      "data": {
        "npm": 123,
        "url": "https://example.com/module",
        "local": "/path/to/local/module",
        "args": "--arg1 --arg2"
      }
    },
    {
      "description": "llama-70b generated negative",
      "valid": false,
      "rust_error": "Additional properties are not allowed ('extra' was unexpected)",
      "python_error": "Additional properties are not allowed ('extra' was unexpected)\n\nFailed validating 'additionalProperties' in schema:\n    {'$schema': 'http://json-schema.org/draft-04/schema#',\n     'title': 'UiModuleDescriptor',\n     'description': 'UI Module description',\n     'type': ['object', 'null'],\n     'additionalProperties': False,\n     'properties': {'npm': {'description': 'NPM module',\n                            'type': ['string', 'null']},\n                    'url': {'description': 'URL',\n                            'type': ['string', 'null']},\n                    'local': {'description': 'Local',\n                              'type': ['string', 'null']},\n                    'args': {'description': 'Arguments',\n                             'type': ['string', 'null']}}}\n\nOn instance:\n    {'npm': 'module-name',\n     'url': 'https://example.com/module',\n     'local': '/path/to/local/module',\n     'args': '--arg1 --arg2',\n     'extra': 'this is an extra property'}",
      "data": {
        "npm": "module-name",
        "url": "https://example.com/module",
        "local": "/path/to/local/module",
        "args": "--arg1 --arg2",
        "extra": "this is an extra property"
      }
    }
  ]
}