{
  "description": "sample Github_easy/o58916.json",
  "meta": {
    "full_size": 338,
    "stripped_size": 338,
    "features": [
      "additionalProperties",
      "format",
      "format:email"
    ],
    "raw_features": [
      "$schema",
      "_boolSchema",
      "properties",
      "required",
      "type",
      "type:object",
      "type:string"
    ]
  },
  "schema": {
    "$schema": "http://json-schema.org/draft-04/schema#",
    "type": "object",
    "properties": {
      "person": {
        "properties": {
          "name": {
            "type": "string"
          },
          "email": {
            "type": "string",
            "format": "email"
          },
          "phone_number": {
            "type": "string"
          },
          "title": {
            "type": "string"
          }
        },
        "required": [
          "email"
        ],
        "additionalProperties": false
      }
    },
    "required": [
      "person"
    ],
    "additionalProperties": false
  },
  "tests": [
    {
      "description": "llama 70b generated valid",
      "valid": true,
      "data": {
        "person": {
          "name": "John Doe",
          "email": "john.doe@example.com",
          "phone_number": "123-456-7890",
          "title": "Software Engineer"
        }
      }
    },
    {
      "description": "llama-70b generated negative; focus on format keyword",
      "valid": false,
      "rust_error": "\"invalid_email\" is not a \"email\"",
      "python_error": "'invalid_email' is not a 'email'\n\nFailed validating 'format' in schema['properties']['person']['properties']['email']:\n    {'type': 'string', 'format': 'email'}\n\nOn instance['person']['email']:\n    'invalid_email'",
      "data": {
        "person": {
          "name": "John Doe",
          "email": "invalid_email",
          "phone_number": "123-456-7890",
          "title": "Software Engineer"
        }
      }
    },
    {
      "description": "llama-70b generated negative",
      "valid": false,
      "rust_error": "Additional properties are not allowed ('address' was unexpected)",
      "python_error": "Additional properties are not allowed ('address' was unexpected)\n\nFailed validating 'additionalProperties' in schema['properties']['person']:\n    {'properties': {'name': {'type': 'string'},\n                    'email': {'type': 'string', 'format': 'email'},\n                    'phone_number': {'type': 'string'},\n                    'title': {'type': 'string'}},\n     'required': ['email'],\n     'additionalProperties': False}\n\nOn instance['person']:\n    {'name': 'John Doe',\n     'email': 'john.doe@example.com',\n     'phone_number': '123-456-7890',\n     'title': 'Software Engineer',\n     'address': '123 Main St'}",
      "data": {
        "person": {
          "name": "John Doe",
          "email": "john.doe@example.com",
          "phone_number": "123-456-7890",
          "title": "Software Engineer",
          "address": "123 Main St"
        }
      }
    },
    {
      "description": "llama-70b generated negative",
      "valid": false,
      "rust_error": "Additional properties are not allowed ('extra_property' was unexpected)",
      "python_error": "Additional properties are not allowed ('extra_property' was unexpected)\n\nFailed validating 'additionalProperties' in schema['properties']['person']:\n    {'properties': {'name': {'type': 'string'},\n                    'email': {'type': 'string', 'format': 'email'},\n                    'phone_number': {'type': 'string'},\n                    'title': {'type': 'string'}},\n     'required': ['email'],\n     'additionalProperties': False}\n\nOn instance['person']:\n    {'name': 'John Doe',\n     'email': 'john.doe@example.com',\n     'phone_number': '123-456-7890',\n     'title': 'Software Engineer',\n     'extra_property': 'Invalid'}",
      "data": {
        "person": {
          "name": "John Doe",
          "email": "john.doe@example.com",
          "phone_number": "123-456-7890",
          "title": "Software Engineer",
          "extra_property": "Invalid"
        }
      }
    }
  ]
}