{
  "description": "sample Github_easy/o21490.json",
  "meta": {
    "full_size": 332,
    "stripped_size": 283,
    "features": [
      "additionalProperties",
      "items"
    ],
    "raw_features": [
      "_boolSchema",
      "properties",
      "type",
      "type:array",
      "type:boolean",
      "type:number",
      "type:object",
      "type:string"
    ]
  },
  "schema": {
    "additionalProperties": false,
    "properties": {
      "additionalFields": {
        "type": "object"
      },
      "chunk-size": {
        "type": "number"
      },
      "empty-data-set": {
        "type": "boolean"
      },
      "idMapping": {
        "items": {
          "type": "string"
        },
        "type": "array"
      },
      "mappings": {
        "type": "object"
      },
      "row_type_name": {
        "type": "string"
      }
    },
    "title": "Webtrends Keymetrics Collector Options",
    "type": "object"
  },
  "tests": [
    {
      "description": "llama 70b generated valid",
      "valid": true,
      "data": {
        "additionalFields": {
          "field1": "value1",
          "field2": "value2"
        },
        "chunk-size": 100,
        "empty-data-set": false,
        "idMapping": [
          "id1",
          "id2",
          "id3"
        ],
        "mappings": {
          "mapping1": "value1",
          "mapping2": "value2"
        },
        "row_type_name": "my_row_type"
      }
    },
    {
      "description": "llama-70b generated negative",
      "valid": false,
      "rust_error": "Additional properties are not allowed ('extraField' was unexpected)",
      "python_error": "Additional properties are not allowed ('extraField' was unexpected)\n\nFailed validating 'additionalProperties' in schema:\n    {'additionalProperties': False,\n     'properties': {'additionalFields': {'type': 'object'},\n                    'chunk-size': {'type': 'number'},\n                    'empty-data-set': {'type': 'boolean'},\n                    'idMapping': {'items': {'type': 'string'},\n                                  'type': 'array'},\n                    'mappings': {'type': 'object'},\n                    'row_type_name': {'type': 'string'}},\n     'title': 'Webtrends Keymetrics Collector Options',\n     'type': 'object'}\n\nOn instance:\n    {'additionalFields': {'field1': 'value1', 'field2': 'value2'},\n     'chunk-size': 100,\n     'empty-data-set': False,\n     'idMapping': ['id1', 'id2', 'id3'],\n     'mappings': {'mapping1': 'value1', 'mapping2': 'value2'},\n     'row_type_name': 'my_row_type',\n     'extraField': 'extraValue'}",
      "data": {
        "additionalFields": {
          "field1": "value1",
          "field2": "value2"
        },
        "chunk-size": 100,
        "empty-data-set": false,
        "idMapping": [
          "id1",
          "id2",
          "id3"
        ],
        "mappings": {
          "mapping1": "value1",
          "mapping2": "value2"
        },
        "row_type_name": "my_row_type",
        "extraField": "extraValue"
      }
    },
    {
      "description": "llama-70b generated negative",
      "valid": false,
      "rust_error": "123 is not of type \"string\"",
      "python_error": "Additional properties are not allowed ('extraField' was unexpected)\n\nFailed validating 'additionalProperties' in schema:\n    {'additionalProperties': False,\n     'properties': {'additionalFields': {'type': 'object'},\n                    'chunk-size': {'type': 'number'},\n                    'empty-data-set': {'type': 'boolean'},\n                    'idMapping': {'items': {'type': 'string'},\n                                  'type': 'array'},\n                    'mappings': {'type': 'object'},\n                    'row_type_name': {'type': 'string'}},\n     'title': 'Webtrends Keymetrics Collector Options',\n     'type': 'object'}\n\nOn instance:\n    {'additionalFields': {'field1': 'value1', 'field2': 'value2'},\n     'chunk-size': 100,\n     'empty-data-set': False,\n     'idMapping': ['id1', 123, 'id3'],\n     'mappings': {'mapping1': 'value1', 'mapping2': 'value2'},\n     'row_type_name': 'my_row_type',\n     'extraField': 'extraValue'}",
      "data": {
        "additionalFields": {
          "field1": "value1",
          "field2": "value2"
        },
        "chunk-size": 100,
        "empty-data-set": false,
        "idMapping": [
          "id1",
          123,
          "id3"
        ],
        "mappings": {
          "mapping1": "value1",
          "mapping2": "value2"
        },
        "row_type_name": "my_row_type",
        "extraField": "extraValue"
      }
    }
  ]
}