{
  "description": "sample Github_easy/o24182.json",
  "meta": {
    "full_size": 335,
    "stripped_size": 301,
    "features": [
      "additionalProperties",
      "items"
    ],
    "raw_features": [
      "$schema",
      "_boolSchema",
      "properties",
      "type",
      "type:array",
      "type:boolean",
      "type:object",
      "type:string"
    ]
  },
  "schema": {
    "$schema": "http://json-schema.org/draft-04/schema#",
    "title": "Okapi Permission Object",
    "type": "object",
    "properties": {
      "permissionName": {
        "type": "string"
      },
      "displayName": {
        "type": "string"
      },
      "description": {
        "type": "string"
      },
      "subPermissions": {
        "type": "array",
        "items": {
          "type": "string"
        }
      },
      "visible": {
        "type": "boolean"
      }
    },
    "additionalProperties": false
  },
  "tests": [
    {
      "description": "llama 70b generated valid",
      "valid": true,
      "data": {
        "permissionName": "example_permission",
        "displayName": "Example Permission",
        "description": "This is an example permission.",
        "subPermissions": [
          "sub_permission_1",
          "sub_permission_2"
        ],
        "visible": true
      }
    },
    {
      "description": "llama-70b generated negative",
      "valid": false,
      "rust_error": "Additional properties are not allowed ('invalidProperty' was unexpected)",
      "python_error": "Additional properties are not allowed ('invalidProperty' was unexpected)\n\nFailed validating 'additionalProperties' in schema:\n    {'$schema': 'http://json-schema.org/draft-04/schema#',\n     'title': 'Okapi Permission Object',\n     'type': 'object',\n     'properties': {'permissionName': {'type': 'string'},\n                    'displayName': {'type': 'string'},\n                    'description': {'type': 'string'},\n                    'subPermissions': {'type': 'array',\n                                       'items': {'type': 'string'}},\n                    'visible': {'type': 'boolean'}},\n     'additionalProperties': False}\n\nOn instance:\n    {'permissionName': 'example_permission',\n     'displayName': 'Example Permission',\n     'description': 'This is an example permission.',\n     'subPermissions': ['sub_permission_1', 'sub_permission_2'],\n     'visible': True,\n     'invalidProperty': 'This is an invalid property'}",
      "data": {
        "permissionName": "example_permission",
        "displayName": "Example Permission",
        "description": "This is an example permission.",
        "subPermissions": [
          "sub_permission_1",
          "sub_permission_2"
        ],
        "visible": true,
        "invalidProperty": "This is an invalid property"
      }
    },
    {
      "description": "llama-70b generated negative",
      "valid": false,
      "rust_error": "123 is not of type \"string\"",
      "python_error": "Additional properties are not allowed ('extraProperty' was unexpected)\n\nFailed validating 'additionalProperties' in schema:\n    {'$schema': 'http://json-schema.org/draft-04/schema#',\n     'title': 'Okapi Permission Object',\n     'type': 'object',\n     'properties': {'permissionName': {'type': 'string'},\n                    'displayName': {'type': 'string'},\n                    'description': {'type': 'string'},\n                    'subPermissions': {'type': 'array',\n                                       'items': {'type': 'string'}},\n                    'visible': {'type': 'boolean'}},\n     'additionalProperties': False}\n\nOn instance:\n    {'permissionName': 'example_permission',\n     'displayName': 'Example Permission',\n     'description': 'This is an example permission.',\n     'subPermissions': ['sub_permission_1', 123],\n     'visible': True,\n     'extraProperty': 'extraValue'}",
      "data": {
        "permissionName": "example_permission",
        "displayName": "Example Permission",
        "description": "This is an example permission.",
        "subPermissions": [
          "sub_permission_1",
          123
        ],
        "visible": true,
        "extraProperty": "extraValue"
      }
    },
    {
      "description": "llama 70b generated positive",
      "valid": true,
      "data": {
        "permissionName": "MANAGE_USERS",
        "displayName": "Manage Users",
        "description": "Permission to manage user accounts",
        "subPermissions": [
          "CREATE_USER",
          "UPDATE_USER",
          "DELETE_USER"
        ],
        "visible": true
      }
    },
    {
      "description": "llama-70b generated negative",
      "valid": false,
      "rust_error": "null is not of type \"string\"",
      "python_error": "Additional properties are not allowed ('extraProperty' was unexpected)\n\nFailed validating 'additionalProperties' in schema:\n    {'$schema': 'http://json-schema.org/draft-04/schema#',\n     'title': 'Okapi Permission Object',\n     'type': 'object',\n     'properties': {'permissionName': {'type': 'string'},\n                    'displayName': {'type': 'string'},\n                    'description': {'type': 'string'},\n                    'subPermissions': {'type': 'array',\n                                       'items': {'type': 'string'}},\n                    'visible': {'type': 'boolean'}},\n     'additionalProperties': False}\n\nOn instance:\n    {'permissionName': 'MANAGE_USERS',\n     'displayName': 'Manage Users',\n     'description': 'Permission to manage user accounts',\n     'subPermissions': ['CREATE_USER', 'UPDATE_USER', None],\n     'visible': True,\n     'extraProperty': 'This is an extra property'}",
      "data": {
        "permissionName": "MANAGE_USERS",
        "displayName": "Manage Users",
        "description": "Permission to manage user accounts",
        "subPermissions": [
          "CREATE_USER",
          "UPDATE_USER",
          null
        ],
        "visible": true,
        "extraProperty": "This is an extra property"
      }
    }
  ]
}