{
  "description": "sample Github_easy/o10514.json",
  "meta": {
    "full_size": 459,
    "stripped_size": 426,
    "features": [
      "additionalProperties",
      "enum"
    ],
    "raw_features": [
      "_boolSchema",
      "properties",
      "required",
      "type",
      "type:object",
      "type:string"
    ]
  },
  "schema": {
    "additionalProperties": false,
    "properties": {
      "Address": {
        "additionalProperties": false,
        "properties": {
          "Country": {
            "enum": [
              "IN",
              "DE",
              "ES",
              "UK",
              "US"
            ],
            "type": "string"
          },
          "County": {
            "type": "string"
          },
          "House": {
            "type": "string"
          },
          "PostCode": {
            "type": "string"
          },
          "Recipient": {
            "type": "string"
          },
          "Street": {
            "type": "string"
          },
          "Town": {
            "type": "string"
          }
        },
        "required": [
          "Recipient",
          "House",
          "Street",
          "Town",
          "PostCode"
        ]
      }
    },
    "required": [
      "Address"
    ],
    "title": "test/addressSchema.xsd",
    "type": "object"
  },
  "tests": [
    {
      "description": "llama 70b generated valid",
      "valid": true,
      "data": {
        "Address": {
          "Country": "UK",
          "County": "London",
          "House": "123",
          "PostCode": "SW1A 0AA",
          "Recipient": "John Doe",
          "Street": "Downing Street",
          "Town": "London"
        }
      }
    },
    {
      "description": "llama-70b generated negative",
      "valid": false,
      "rust_error": "\"FR\" is not one of [\"IN\",\"DE\",\"ES\",\"UK\",\"US\"]",
      "python_error": "Additional properties are not allowed ('123', 'Downing Street', 'Invalid Value', 'Invalid country, not in the enum list', 'John Doe', 'London', 'SW1A 0AA' were unexpected)\n\nFailed validating 'additionalProperties' in schema['properties']['Address']:\n    {'additionalProperties': False,\n     'properties': {'Country': {'enum': ['IN', 'DE', 'ES', 'UK', 'US'],\n                                'type': 'string'},\n                    'County': {'type': 'string'},\n                    'House': {'type': 'string'},\n                    'PostCode': {'type': 'string'},\n                    'Recipient': {'type': 'string'},\n                    'Street': {'type': 'string'},\n                    'Town': {'type': 'string'}},\n     'required': ['Recipient', 'House', 'Street', 'Town', 'PostCode']}\n\nOn instance['Address']:\n    {'Country': 'FR',\n     'Invalid country, not in the enum list': 'County',\n     'London': 'InvalidProperty',\n     '123': 'PostCode',\n     'SW1A 0AA': 'Recipient',\n     'John Doe': 'Street',\n     'Downing Street': 'Town',\n     'Invalid Value': 'additionalProperties'}",
      "data": {
        "Address": {
          "Country": "FR",
          "Invalid country, not in the enum list": "County",
          "London": "InvalidProperty",
          "123": "PostCode",
          "SW1A 0AA": "Recipient",
          "John Doe": "Street",
          "Downing Street": "Town",
          "Invalid Value": "additionalProperties"
        }
      }
    },
    {
      "description": "llama-70b generated negative",
      "valid": false,
      "rust_error": "\"FR\" is not one of [\"IN\",\"DE\",\"ES\",\"UK\",\"US\"]",
      "python_error": "Additional properties are not allowed ('Invalid country code, not in the enum list', \"Invalid property name, should be 'County'\" were unexpected)\n\nFailed validating 'additionalProperties' in schema['properties']['Address']:\n    {'additionalProperties': False,\n     'properties': {'Country': {'enum': ['IN', 'DE', 'ES', 'UK', 'US'],\n                                'type': 'string'},\n                    'County': {'type': 'string'},\n                    'House': {'type': 'string'},\n                    'PostCode': {'type': 'string'},\n                    'Recipient': {'type': 'string'},\n                    'Street': {'type': 'string'},\n                    'Town': {'type': 'string'}},\n     'required': ['Recipient', 'House', 'Street', 'Town', 'PostCode']}\n\nOn instance['Address']:\n    {'Country': 'FR',\n     'Invalid country code, not in the enum list': 'County',\n     \"Invalid property name, should be 'County'\": 'London',\n     'House': '123',\n     'PostCode': 'SW1A 0AA',\n     'Recipient': 'John Doe',\n     'Street': 'Downing Street',\n     'Town': 'London'}",
      "data": {
        "Address": {
          "Country": "FR",
          "Invalid country code, not in the enum list": "County",
          "Invalid property name, should be 'County'": "London",
          "House": "123",
          "PostCode": "SW1A 0AA",
          "Recipient": "John Doe",
          "Street": "Downing Street",
          "Town": "London"
        }
      }
    },
    {
      "description": "llama-70b generated negative",
      "valid": false,
      "rust_error": "\"FR\" is not one of [\"IN\",\"DE\",\"ES\",\"UK\",\"US\"]",
      "python_error": "Additional properties are not allowed ('Intentionally added a colon instead of a comma after County property to check if the validator validates the overall JSON syntax', 'Invalid country code, FR is not in the enum list' were unexpected)\n\nFailed validating 'additionalProperties' in schema['properties']['Address']:\n    {'additionalProperties': False,\n     'properties': {'Country': {'enum': ['IN', 'DE', 'ES', 'UK', 'US'],\n                                'type': 'string'},\n                    'County': {'type': 'string'},\n                    'House': {'type': 'string'},\n                    'PostCode': {'type': 'string'},\n                    'Recipient': {'type': 'string'},\n                    'Street': {'type': 'string'},\n                    'Town': {'type': 'string'}},\n     'required': ['Recipient', 'House', 'Street', 'Town', 'PostCode']}\n\nOn instance['Address']:\n    {'Country': 'FR',\n     'Invalid country code, FR is not in the enum list': 'County',\n     'Intentionally added a colon instead of a comma after C.. (222 more)",
      "data": {
        "Address": {
          "Country": "FR",
          "Invalid country code, FR is not in the enum list": "County",
          "Intentionally added a colon instead of a comma after County property to check if the validator validates the overall JSON syntax": "London",
          "House": "123",
          "PostCode": "SW1A 0AA",
          "Recipient": "John Doe",
          "Street": "Downing Street",
          "Town": "London"
        }
      }
    }
  ]
}