{
  "description": "sample Github_easy/o12085.json",
  "meta": {
    "full_size": 398,
    "stripped_size": 296,
    "features": [
      "additionalProperties",
      "items"
    ],
    "raw_features": [
      "_boolSchema",
      "properties",
      "required",
      "type",
      "type:array",
      "type:number",
      "type:object",
      "type:string"
    ]
  },
  "schema": {
    "additionalProperties": false,
    "items": {
      "additionalProperties": false,
      "properties": {
        "creator": {
          "type": "string"
        },
        "creatorScore": {
          "type": "number"
        },
        "lastEventId": {
          "type": "string"
        },
        "photographer": {
          "type": "string"
        },
        "productId": {
          "type": "string"
        }
      },
      "required": [
        "productId"
      ],
      "type": "object"
    },
    "self": {
      "format": "jsonschema",
      "name": "contribution/items",
      "vendor": "com.nordstrom",
      "version": "1-0-0"
    },
    "type": "array"
  },
  "tests": [
    {
      "description": "llama 70b generated valid",
      "valid": true,
      "data": [
        {
          "creator": "John Doe",
          "creatorScore": 90.5,
          "lastEventId": "event-12345",
          "photographer": "Jane Doe",
          "productId": "product-123"
        },
        {
          "creator": "Alice Smith",
          "creatorScore": 85.2,
          "lastEventId": "event-67890",
          "photographer": "Bob Johnson",
          "productId": "product-456"
        }
      ]
    },
    {
      "description": "llama-70b generated negative",
      "valid": false,
      "rust_error": "False schema does not allow \"John Doe\"",
      "python_error": "Additional properties are not allowed ('creator', 'creatorScore', 'extraProperty', 'lastEventId', 'photographer', 'productId' were unexpected)\n\nFailed validating 'additionalProperties' in schema:\n    {'additionalProperties': False,\n     'items': {'additionalProperties': False,\n               'properties': {'creator': {'type': 'string'},\n                              'creatorScore': {'type': 'number'},\n                              'lastEventId': {'type': 'string'},\n                              'photographer': {'type': 'string'},\n                              'productId': {'type': 'string'}},\n               'required': ['productId'],\n               'type': 'object'},\n     'self': {'format': 'jsonschema',\n              'name': 'contribution/items',\n              'vendor': 'com.nordstrom',\n              'version': '1-0-0'},\n     'type': 'array'}\n\nOn instance:\n    {'creator': 'John Doe',\n     'creatorScore': 90.5,\n     'lastEventId': 'event-12345',\n     'photographer': 'Jane Doe',\n     'productId': 'product-123',\n     'extraProperty': 'Invalid'}",
      "data": {
        "creator": "John Doe",
        "creatorScore": 90.5,
        "lastEventId": "event-12345",
        "photographer": "Jane Doe",
        "productId": "product-123",
        "extraProperty": "Invalid"
      }
    },
    {
      "description": "llama-70b generated negative",
      "valid": false,
      "rust_error": "False schema does not allow false",
      "python_error": "Additional properties are not allowed ('additionalProperties', 'items', 'self', 'type' were unexpected)\n\nFailed validating 'additionalProperties' in schema:\n    {'additionalProperties': False,\n     'items': {'additionalProperties': False,\n               'properties': {'creator': {'type': 'string'},\n                              'creatorScore': {'type': 'number'},\n                              'lastEventId': {'type': 'string'},\n                              'photographer': {'type': 'string'},\n                              'productId': {'type': 'string'}},\n               'required': ['productId'],\n               'type': 'object'},\n     'self': {'format': 'jsonschema',\n              'name': 'contribution/items',\n              'vendor': 'com.nordstrom',\n              'version': '1-0-0'},\n     'type': 'array'}\n\nOn instance:\n    {'additionalProperties': False,\n     'items': {'additionalProperties': False,\n               'properties': {'creator': {'type': 'string'},\n                              'creatorScore': {'ty.. (466 more)",
      "data": {
        "additionalProperties": false,
        "items": {
          "additionalProperties": false,
          "properties": {
            "creator": {
              "type": "string"
            },
            "creatorScore": {
              "type": "number"
            },
            "lastEventId": {
              "type": "string"
            },
            "photographer": {
              "type": "string"
            },
            "productId": {
              "type": "string"
            }
          },
          "required": [
            "productId"
          ],
          "type": "object"
        },
        "self": {
          "format": "jsonschema",
          "name": "contribution/items",
          "vendor": "com.nordstrom",
          "version": "1-0-0"
        },
        "type": "array"
      }
    }
  ]
}