{
  "description": "sample Github_easy/o39428.json",
  "meta": {
    "full_size": 331,
    "stripped_size": 268,
    "features": [
      "additionalProperties",
      "format",
      "format:date-time"
    ],
    "raw_features": [
      "$schema",
      "_boolSchema",
      "properties",
      "type",
      "type:object",
      "type:string"
    ]
  },
  "schema": {
    "$schema": "http://json-schema.org/draft-04/schema#",
    "title": "CreateTokenResponse",
    "type": "object",
    "additionalProperties": false,
    "properties": {
      "id": {
        "type": "string"
      },
      "createdAt": {
        "type": "string",
        "format": "date-time"
      },
      "expiresAt": {
        "type": "string",
        "format": "date-time"
      },
      "authToken": {
        "type": "string"
      }
    },
    "javaName": "CreateTokenResponse"
  },
  "tests": [
    {
      "description": "llama 70b generated valid",
      "valid": true,
      "data": {
        "id": "token-12345",
        "createdAt": "2022-01-01T12:00:00Z",
        "expiresAt": "2022-01-01T13:00:00Z",
        "authToken": "eyJhbGciOiJIUzI1NiIsInR5cCI6IkpXVCJ9.eyJzdWIiOiIxMjM0NTY3ODkwIiwibmFtZSI6IkpvaGFuIjoiMjMwfQ.SflKxwRJSMeKKF2QT4fwpMeJf36POk6yJV_adQssw5c"
      }
    },
    {
      "description": "llama-70b generated negative; focus on format keyword",
      "valid": false,
      "rust_error": "\"2022-01-01 12:00:00\" is not a \"date-time\"",
      "python_error": "'2022-01-01 12:00:00' is not a 'date-time'\n\nFailed validating 'format' in schema['properties']['createdAt']:\n    {'type': 'string', 'format': 'date-time'}\n\nOn instance['createdAt']:\n    '2022-01-01 12:00:00'",
      "data": {
        "id": "token-12345",
        "createdAt": "2022-01-01 12:00:00",
        "expiresAt": "2022-01-01T13:00:00Z",
        "authToken": "eyJhbGciOiJIUzI1NiIsInR5cCI6IkpXVCJ9.eyJzdWIiOiIxMjM0NTY3ODkwIiwibmFtZSI6IkpvaGFuIjoiMjMwfQ.SflKxwRJSMeKKF2QT4fwpMeJf36POk6yJV_adQssw5c"
      }
    },
    {
      "description": "llama-70b generated negative",
      "valid": false,
      "rust_error": "Additional properties are not allowed ('extraProperty' was unexpected)",
      "python_error": "Additional properties are not allowed ('extraProperty' was unexpected)\n\nFailed validating 'additionalProperties' in schema:\n    {'$schema': 'http://json-schema.org/draft-04/schema#',\n     'title': 'CreateTokenResponse',\n     'type': 'object',\n     'additionalProperties': False,\n     'properties': {'id': {'type': 'string'},\n                    'createdAt': {'type': 'string', 'format': 'date-time'},\n                    'expiresAt': {'type': 'string', 'format': 'date-time'},\n                    'authToken': {'type': 'string'}},\n     'javaName': 'CreateTokenResponse'}\n\nOn instance:\n    {'id': 'token-12345',\n     'createdAt': '2022-01-01T12:00:00Z',\n     'expiresAt': '2022-01-01T13:00:00Z',\n     'authToken': 'eyJhbGciOiJIUzI1NiIsInR5cCI6IkpXVCJ9.eyJzdWIiOiIxMjM0NTY3ODkwIiwibmFtZSI6IkpvaGFuIjoiMjMwfQ.SflKxwRJSMeKKF2QT4fwpMeJf36POk6yJV_adQssw5c',\n     'extraProperty': 'extraValue'}",
      "data": {
        "id": "token-12345",
        "createdAt": "2022-01-01T12:00:00Z",
        "expiresAt": "2022-01-01T13:00:00Z",
        "authToken": "eyJhbGciOiJIUzI1NiIsInR5cCI6IkpXVCJ9.eyJzdWIiOiIxMjM0NTY3ODkwIiwibmFtZSI6IkpvaGFuIjoiMjMwfQ.SflKxwRJSMeKKF2QT4fwpMeJf36POk6yJV_adQssw5c",
        "extraProperty": "extraValue"
      }
    },
    {
      "description": "llama-70b generated negative; focus on format keyword",
      "valid": false,
      "rust_error": "\"2022-01-01T12:00:00\" is not a \"date-time\"",
      "python_error": "'2022-01-01T12:00:00' is not a 'date-time'\n\nFailed validating 'format' in schema['properties']['createdAt']:\n    {'type': 'string', 'format': 'date-time'}\n\nOn instance['createdAt']:\n    '2022-01-01T12:00:00'",
      "data": {
        "id": "token-12345",
        "createdAt": "2022-01-01T12:00:00",
        "expiresAt": "2022-01-01T13:00:00Z",
        "authToken": "eyJhbGciOiJIUzI1NiIsInR5cCI6IkpXVCJ9.eyJzdWIiOiIxMjM0NTY3ODkwIiwibmFtZSI6IkpvaGFuIjoiMjMwfQ.SflKxwRJSMeKKF2QT4fwpMeJf36POk6yJV_adQssw5c"
      }
    },
    {
      "description": "llama-70b generated negative",
      "valid": false,
      "rust_error": "\"2022-01-01T13:00:00\" is not a \"date-time\"",
      "python_error": "Additional properties are not allowed ('extraField' was unexpected)\n\nFailed validating 'additionalProperties' in schema:\n    {'$schema': 'http://json-schema.org/draft-04/schema#',\n     'title': 'CreateTokenResponse',\n     'type': 'object',\n     'additionalProperties': False,\n     'properties': {'id': {'type': 'string'},\n                    'createdAt': {'type': 'string', 'format': 'date-time'},\n                    'expiresAt': {'type': 'string', 'format': 'date-time'},\n                    'authToken': {'type': 'string'}},\n     'javaName': 'CreateTokenResponse'}\n\nOn instance:\n    {'id': 'token-12345',\n     'createdAt': '2022-01-01T12:00:00Z',\n     'expiresAt': '2022-01-01T13:00:00',\n     'authToken': 'eyJhbGciOiJIUzI1NiIsInR5cCI6IkpXVCJ9.eyJzdWIiOiIxMjM0NTY3ODkwIiwibmFtZSI6IkpvaGFuIjoiMjMwfQ.SflKxwRJSMeKKF2QT4fwpMeJf36POk6yJV_adQssw5c',\n     'extraField': 'extraValue'}",
      "data": {
        "id": "token-12345",
        "createdAt": "2022-01-01T12:00:00Z",
        "expiresAt": "2022-01-01T13:00:00",
        "authToken": "eyJhbGciOiJIUzI1NiIsInR5cCI6IkpXVCJ9.eyJzdWIiOiIxMjM0NTY3ODkwIiwibmFtZSI6IkpvaGFuIjoiMjMwfQ.SflKxwRJSMeKKF2QT4fwpMeJf36POk6yJV_adQssw5c",
        "extraField": "extraValue"
      }
    },
    {
      "description": "llama-70b generated negative",
      "valid": false,
      "rust_error": "Additional properties are not allowed ('additionalProperty' was unexpected)",
      "python_error": "Additional properties are not allowed ('additionalProperty' was unexpected)\n\nFailed validating 'additionalProperties' in schema:\n    {'$schema': 'http://json-schema.org/draft-04/schema#',\n     'title': 'CreateTokenResponse',\n     'type': 'object',\n     'additionalProperties': False,\n     'properties': {'id': {'type': 'string'},\n                    'createdAt': {'type': 'string', 'format': 'date-time'},\n                    'expiresAt': {'type': 'string', 'format': 'date-time'},\n                    'authToken': {'type': 'string'}},\n     'javaName': 'CreateTokenResponse'}\n\nOn instance:\n    {'id': '',\n     'createdAt': '2022-01-01T12:00:00Z',\n     'expiresAt': '2022-01-01T13:00:00Z',\n     'authToken': 'eyJhbGciOiJIUzI1NiIsInR5cCI6IkpXVCJ9.eyJzdWIiOiIxMjM0NTY3ODkwIiwibmFtZSI6IkpvaGFuIjoiMjMwfQ.SflKxwRJSMeKKF2QT4fwpMeJf36POk6yJV_adQssw5c',\n     'additionalProperty': 'extraValue'}",
      "data": {
        "id": "",
        "createdAt": "2022-01-01T12:00:00Z",
        "expiresAt": "2022-01-01T13:00:00Z",
        "authToken": "eyJhbGciOiJIUzI1NiIsInR5cCI6IkpXVCJ9.eyJzdWIiOiIxMjM0NTY3ODkwIiwibmFtZSI6IkpvaGFuIjoiMjMwfQ.SflKxwRJSMeKKF2QT4fwpMeJf36POk6yJV_adQssw5c",
        "additionalProperty": "extraValue"
      }
    }
  ]
}