{
  "description": "sample Github_easy/o79513.json",
  "meta": {
    "full_size": 436,
    "stripped_size": 368,
    "features": [
      "additionalProperties",
      "enum"
    ],
    "raw_features": [
      "$schema",
      "_boolSchema",
      "properties",
      "type",
      "type:number",
      "type:object",
      "type:string"
    ]
  },
  "schema": {
    "$schema": "http://json-schema.org/draft-04/schema#",
    "type": "object",
    "description": "Advertisement status for the supplied advertisement",
    "properties": {
      "advertisementId": {
        "type": "string"
      },
      "status": {
        "enum": [
          "open",
          "expired"
        ]
      },
      "postedBy": {
        "type": "string"
      },
      "datePosted": {
        "type": "number"
      },
      "expiredBy": {
        "type": "string"
      },
      "dateExpired": {
        "type": "number"
      },
      "title": {
        "type": "string"
      },
      "referenceCode": {
        "type": "string"
      }
    },
    "additionalProperties": false
  },
  "tests": [
    {
      "description": "llama 70b generated valid",
      "valid": true,
      "data": {
        "advertisementId": "AD-12345",
        "status": "expired",
        "postedBy": "John Doe",
        "datePosted": 1643723400,
        "expiredBy": "Jane Doe",
        "dateExpired": 1646315200,
        "title": "Example Advertisement",
        "referenceCode": "REF-12345"
      }
    },
    {
      "description": "llama-70b generated negative",
      "valid": false,
      "rust_error": "\"pending\" is not one of [\"open\",\"expired\"]",
      "python_error": "Additional properties are not allowed ('extraField' was unexpected)\n\nFailed validating 'additionalProperties' in schema:\n    {'$schema': 'http://json-schema.org/draft-04/schema#',\n     'type': 'object',\n     'description': 'Advertisement status for the supplied advertisement',\n     'properties': {'advertisementId': {'type': 'string'},\n                    'status': {'enum': ['open', 'expired']},\n                    'postedBy': {'type': 'string'},\n                    'datePosted': {'type': 'number'},\n                    'expiredBy': {'type': 'string'},\n                    'dateExpired': {'type': 'number'},\n                    'title': {'type': 'string'},\n                    'referenceCode': {'type': 'string'}},\n     'additionalProperties': False}\n\nOn instance:\n    {'advertisementId': 'AD-12345',\n     'status': 'pending',\n     'expiredBy': 'Jane Doe',\n     'dateExpired': 1646315200,\n     'title': 'Example Advertisement',\n     'referenceCode': 'REF-12345',\n     'postedBy': 'John Doe',\n     'datePosted': 1643723400,\n     'extraField': 'extraValue'}",
      "data": {
        "advertisementId": "AD-12345",
        "status": "pending",
        "expiredBy": "Jane Doe",
        "dateExpired": 1646315200,
        "title": "Example Advertisement",
        "referenceCode": "REF-12345",
        "postedBy": "John Doe",
        "datePosted": 1643723400,
        "extraField": "extraValue"
      }
    },
    {
      "description": "llama-70b generated negative",
      "valid": false,
      "rust_error": "\"active\" is not one of [\"open\",\"expired\"]",
      "python_error": "Additional properties are not allowed ('extraProperty' was unexpected)\n\nFailed validating 'additionalProperties' in schema:\n    {'$schema': 'http://json-schema.org/draft-04/schema#',\n     'type': 'object',\n     'description': 'Advertisement status for the supplied advertisement',\n     'properties': {'advertisementId': {'type': 'string'},\n                    'status': {'enum': ['open', 'expired']},\n                    'postedBy': {'type': 'string'},\n                    'datePosted': {'type': 'number'},\n                    'expiredBy': {'type': 'string'},\n                    'dateExpired': {'type': 'number'},\n                    'title': {'type': 'string'},\n                    'referenceCode': {'type': 'string'}},\n     'additionalProperties': False}\n\nOn instance:\n    {'advertisementId': 'AD-12345',\n     'status': 'active',\n     'postedBy': 'John Doe',\n     'datePosted': 1643723400,\n     'expiredBy': 'Jane Doe',\n     'dateExpired': 1646315200,\n     'title': 'Example Advertisement',\n     'referenceCode': 'REF-12345',\n     'extraProperty': 'Invalid'}",
      "data": {
        "advertisementId": "AD-12345",
        "status": "active",
        "postedBy": "John Doe",
        "datePosted": 1643723400,
        "expiredBy": "Jane Doe",
        "dateExpired": 1646315200,
        "title": "Example Advertisement",
        "referenceCode": "REF-12345",
        "extraProperty": "Invalid"
      }
    },
    {
      "description": "llama 70b generated positive",
      "valid": true,
      "data": {
        "advertisementId": "AD-12345",
        "status": "expired",
        "postedBy": "John Doe",
        "datePosted": 1643723400,
        "expiredBy": "Jane Doe",
        "dateExpired": 1646315200,
        "title": "Software Engineer Position",
        "referenceCode": "REF-001"
      }
    },
    {
      "description": "llama-70b generated negative",
      "valid": false,
      "rust_error": "\"active\" is not one of [\"open\",\"expired\"]",
      "python_error": "Additional properties are not allowed ('extraProperty' was unexpected)\n\nFailed validating 'additionalProperties' in schema:\n    {'$schema': 'http://json-schema.org/draft-04/schema#',\n     'type': 'object',\n     'description': 'Advertisement status for the supplied advertisement',\n     'properties': {'advertisementId': {'type': 'string'},\n                    'status': {'enum': ['open', 'expired']},\n                    'postedBy': {'type': 'string'},\n                    'datePosted': {'type': 'number'},\n                    'expiredBy': {'type': 'string'},\n                    'dateExpired': {'type': 'number'},\n                    'title': {'type': 'string'},\n                    'referenceCode': {'type': 'string'}},\n     'additionalProperties': False}\n\nOn instance:\n    {'advertisementId': 'AD-12345',\n     'status': 'active',\n     'postedBy': 'John Doe',\n     'datePosted': 1643723400,\n     'expiredBy': 'Jane Doe',\n     'dateExpired': 1646315200,\n     'title': 'Software Engineer Position',\n     'referenceCode': 'REF-001',\n     'extraProperty': 'Invalid'}",
      "data": {
        "advertisementId": "AD-12345",
        "status": "active",
        "postedBy": "John Doe",
        "datePosted": 1643723400,
        "expiredBy": "Jane Doe",
        "dateExpired": 1646315200,
        "title": "Software Engineer Position",
        "referenceCode": "REF-001",
        "extraProperty": "Invalid"
      }
    }
  ]
}