{
  "description": "sample Github_easy/o60758.json",
  "meta": {
    "full_size": 456,
    "stripped_size": 437,
    "features": [
      "additionalProperties",
      "enum"
    ],
    "raw_features": [
      "$schema",
      "_boolSchema",
      "id",
      "properties",
      "required",
      "type",
      "type:number",
      "type:object",
      "type:string"
    ]
  },
  "schema": {
    "id": "http://www.gandhi.io/schema/notification",
    "type": "object",
    "$schema": "http://json-schema.org/draft-04/schema",
    "required": [
      "id",
      "user_id",
      "subject",
      "content"
    ],
    "additionalProperties": false,
    "properties": {
      "id": {
        "type": "string"
      },
      "user_id": {
        "type": "string"
      },
      "subject": {
        "type": "string"
      },
      "content": {
        "type": "string"
      },
      "status_id": {
        "type": "string",
        "enum": [
          "unread",
          "read",
          "archived"
        ],
        "default": "unread"
      },
      "created": {
        "type": "number"
      },
      "updated": {
        "type": "number"
      }
    }
  },
  "tests": [
    {
      "description": "llama 70b generated valid",
      "valid": true,
      "data": {
        "id": "notification-123",
        "user_id": "user-456",
        "subject": "New message from John Doe",
        "content": "Hello, this is a test message.",
        "status_id": "unread",
        "created": 1643723400,
        "updated": 1643723400
      }
    },
    {
      "description": "llama-70b generated negative",
      "valid": false,
      "rust_error": "Additional properties are not allowed ('extra_property' was unexpected)",
      "python_error": "Additional properties are not allowed ('extra_property' was unexpected)\n\nFailed validating 'additionalProperties' in schema:\n    {'id': 'http://www.gandhi.io/schema/notification',\n     'type': 'object',\n     '$schema': 'http://json-schema.org/draft-04/schema',\n     'required': ['id', 'user_id', 'subject', 'content'],\n     'additionalProperties': False,\n     'properties': {'id': {'type': 'string'},\n                    'user_id': {'type': 'string'},\n                    'subject': {'type': 'string'},\n                    'content': {'type': 'string'},\n                    'status_id': {'type': 'string',\n                                  'enum': ['unread', 'read', 'archived'],\n                                  'default': 'unread'},\n                    'created': {'type': 'number'},\n                    'updated': {'type': 'number'}}}\n\nOn instance:\n    {'id': 'notification-123',\n     'user_id': 'user-456',\n     'subject': 'New message from John Doe',\n     'content': 'Hello, this is a test message.',\n     'status_id':.. (118 more)",
      "data": {
        "id": "notification-123",
        "user_id": "user-456",
        "subject": "New message from John Doe",
        "content": "Hello, this is a test message.",
        "status_id": "unread",
        "created": 1643723400,
        "updated": 1643723400,
        "extra_property": "this is an extra property"
      }
    },
    {
      "description": "llama-70b generated negative",
      "valid": false,
      "rust_error": "Additional properties are not allowed ('extra_property' was unexpected)",
      "python_error": "Additional properties are not allowed ('extra_property' was unexpected)\n\nFailed validating 'additionalProperties' in schema:\n    {'id': 'http://www.gandhi.io/schema/notification',\n     'type': 'object',\n     '$schema': 'http://json-schema.org/draft-04/schema',\n     'required': ['id', 'user_id', 'subject', 'content'],\n     'additionalProperties': False,\n     'properties': {'id': {'type': 'string'},\n                    'user_id': {'type': 'string'},\n                    'subject': {'type': 'string'},\n                    'content': {'type': 'string'},\n                    'status_id': {'type': 'string',\n                                  'enum': ['unread', 'read', 'archived'],\n                                  'default': 'unread'},\n                    'created': {'type': 'number'},\n                    'updated': {'type': 'number'}}}\n\nOn instance:\n    {'id': 'notification-123',\n     'user_id': 'user-456',\n     'subject': 'New message from John Doe',\n     'content': 'Hello, this is a test message.',\n     'status_id':.. (116 more)",
      "data": {
        "id": "notification-123",
        "user_id": "user-456",
        "subject": "New message from John Doe",
        "content": "Hello, this is a test message.",
        "status_id": "unread",
        "created": 1643723400,
        "updated": 1643723400,
        "extra_property": "this should not be here"
      }
    },
    {
      "description": "llama 70b generated positive",
      "valid": true,
      "data": {
        "id": "notification-123",
        "user_id": "user-123",
        "subject": "New message from John Doe",
        "content": "Hello, this is a test message.",
        "status_id": "unread",
        "created": 1670400000,
        "updated": 1670400000
      }
    },
    {
      "description": "llama-70b generated negative",
      "valid": false,
      "rust_error": "\"pending\" is not one of [\"unread\",\"read\",\"archived\"]",
      "python_error": "Additional properties are not allowed ('extra_field' was unexpected)\n\nFailed validating 'additionalProperties' in schema:\n    {'id': 'http://www.gandhi.io/schema/notification',\n     'type': 'object',\n     '$schema': 'http://json-schema.org/draft-04/schema',\n     'required': ['id', 'user_id', 'subject', 'content'],\n     'additionalProperties': False,\n     'properties': {'id': {'type': 'string'},\n                    'user_id': {'type': 'string'},\n                    'subject': {'type': 'string'},\n                    'content': {'type': 'string'},\n                    'status_id': {'type': 'string',\n                                  'enum': ['unread', 'read', 'archived'],\n                                  'default': 'unread'},\n                    'created': {'type': 'number'},\n                    'updated': {'type': 'number'}}}\n\nOn instance:\n    {'id': 'notification-123',\n     'user_id': 'user-123',\n     'subject': 'New message from John Doe',\n     'content': 'Hello, this is a test message.',\n     'status_id': 'p.. (98 more)",
      "data": {
        "id": "notification-123",
        "user_id": "user-123",
        "subject": "New message from John Doe",
        "content": "Hello, this is a test message.",
        "status_id": "pending",
        "created": 1670400000,
        "updated": 1670400000,
        "extra_field": "some_value"
      }
    }
  ]
}