{
  "description": "sample Github_easy/o79449.json",
  "meta": {
    "full_size": 289,
    "stripped_size": 289,
    "features": [
      "additionalProperties"
    ],
    "raw_features": [
      "$schema",
      "_boolSchema",
      "properties",
      "required",
      "type",
      "type:object",
      "type:string"
    ]
  },
  "schema": {
    "$schema": "http://json-schema.org/draft-04/schema#",
    "type": "object",
    "properties": {
      "packageName": {
        "type": "string"
      },
      "packageVersion": {
        "type": "string"
      },
      "options": {
        "type": "object",
        "additionalProperties": true
      },
      "appId": {
        "type": "string"
      }
    },
    "required": [
      "packageName"
    ],
    "additionalProperties": false
  },
  "tests": [
    {
      "description": "llama 70b generated valid",
      "valid": true,
      "data": {
        "packageName": "example-package",
        "packageVersion": "1.0.0",
        "options": {
          "debugMode": true,
          "loggingLevel": "INFO"
        },
        "appId": "example-app-id"
      }
    },
    {
      "description": "llama-70b generated negative",
      "valid": false,
      "rust_error": "Additional properties are not allowed ('extraProperty' was unexpected)",
      "python_error": "Additional properties are not allowed ('extraProperty' was unexpected)\n\nFailed validating 'additionalProperties' in schema:\n    {'$schema': 'http://json-schema.org/draft-04/schema#',\n     'type': 'object',\n     'properties': {'packageName': {'type': 'string'},\n                    'packageVersion': {'type': 'string'},\n                    'options': {'type': 'object',\n                                'additionalProperties': True},\n                    'appId': {'type': 'string'}},\n     'required': ['packageName'],\n     'additionalProperties': False}\n\nOn instance:\n    {'packageName': 'example-package',\n     'packageVersion': '1.0.0',\n     'options': {'debugMode': True, 'loggingLevel': 'INFO'},\n     'appId': 'example-app-id',\n     'extraProperty': 'extraValue'}",
      "data": {
        "packageName": "example-package",
        "packageVersion": "1.0.0",
        "options": {
          "debugMode": true,
          "loggingLevel": "INFO"
        },
        "appId": "example-app-id",
        "extraProperty": "extraValue"
      }
    },
    {
      "description": "llama 70b generated positive",
      "valid": true,
      "data": {
        "packageName": "example-package",
        "packageVersion": "1.0.0",
        "options": {
          "option1": "value1",
          "option2": "value2"
        },
        "appId": "example-app-id"
      }
    },
    {
      "description": "llama-70b generated negative",
      "valid": false,
      "rust_error": "Additional properties are not allowed ('extra' was unexpected)",
      "python_error": "Additional properties are not allowed ('extra' was unexpected)\n\nFailed validating 'additionalProperties' in schema:\n    {'$schema': 'http://json-schema.org/draft-04/schema#',\n     'type': 'object',\n     'properties': {'packageName': {'type': 'string'},\n                    'packageVersion': {'type': 'string'},\n                    'options': {'type': 'object',\n                                'additionalProperties': True},\n                    'appId': {'type': 'string'}},\n     'required': ['packageName'],\n     'additionalProperties': False}\n\nOn instance:\n    {'packageName': '',\n     'packageVersion': '1.0.0',\n     'options': {'option1': 'value1', 'option2': 'value2'},\n     'appId': 'example-app-id',\n     'extra': 'extra-value'}",
      "data": {
        "packageName": "",
        "packageVersion": "1.0.0",
        "options": {
          "option1": "value1",
          "option2": "value2"
        },
        "appId": "example-app-id",
        "extra": "extra-value"
      }
    }
  ]
}