{
  "description": "sample Github_easy/o12068.json",
  "meta": {
    "full_size": 266,
    "stripped_size": 168,
    "features": [
      "additionalProperties",
      "items"
    ],
    "raw_features": [
      "_boolSchema",
      "properties",
      "required",
      "type",
      "type:array",
      "type:object",
      "type:string"
    ]
  },
  "schema": {
    "additionalProperties": false,
    "items": {
      "additionalProperties": false,
      "properties": {
        "category": {
          "type": "string"
        }
      },
      "required": [
        "category"
      ],
      "type": "object"
    },
    "self": {
      "format": "jsonschema",
      "name": "category/items",
      "vendor": "com.nordstrom",
      "version": "1-0-0"
    },
    "type": "array"
  },
  "tests": [
    {
      "description": "llama 70b generated valid",
      "valid": true,
      "data": [
        {
          "category": "Electronics"
        },
        {
          "category": "Fashion"
        },
        {
          "category": "Home Goods"
        }
      ]
    },
    {
      "description": "llama-70b generated negative",
      "valid": false,
      "rust_error": "False schema does not allow false",
      "python_error": "Additional properties are not allowed ('additionalProperties', 'items', 'self', 'type' were unexpected)\n\nFailed validating 'additionalProperties' in schema:\n    {'additionalProperties': False,\n     'items': {'additionalProperties': False,\n               'properties': {'category': {'type': 'string'}},\n               'required': ['category'],\n               'type': 'object'},\n     'self': {'format': 'jsonschema',\n              'name': 'category/items',\n              'vendor': 'com.nordstrom',\n              'version': '1-0-0'},\n     'type': 'array'}\n\nOn instance:\n    {'additionalProperties': False,\n     'items': {'additionalProperties': False,\n               'properties': {'category': {'type': 'string'}},\n               'required': ['category'],\n               'type': 'object'},\n     'self': {'format': 'jsonschema',\n              'name': 'category/items',\n              'vendor': 'com.nordstrom',\n              'version': '1-0-0'},\n     'type': 'array'}",
      "data": {
        "additionalProperties": false,
        "items": {
          "additionalProperties": false,
          "properties": {
            "category": {
              "type": "string"
            }
          },
          "required": [
            "category"
          ],
          "type": "object"
        },
        "self": {
          "format": "jsonschema",
          "name": "category/items",
          "vendor": "com.nordstrom",
          "version": "1-0-0"
        },
        "type": "array"
      }
    },
    {
      "description": "llama-70b generated negative",
      "valid": false,
      "rust_error": "False schema does not allow \"Electronics\"",
      "python_error": "Additional properties are not allowed ('category', 'extraProperty' were unexpected)\n\nFailed validating 'additionalProperties' in schema:\n    {'additionalProperties': False,\n     'items': {'additionalProperties': False,\n               'properties': {'category': {'type': 'string'}},\n               'required': ['category'],\n               'type': 'object'},\n     'self': {'format': 'jsonschema',\n              'name': 'category/items',\n              'vendor': 'com.nordstrom',\n              'version': '1-0-0'},\n     'type': 'array'}\n\nOn instance:\n    {'category': 'Electronics', 'extraProperty': 'extraValue'}",
      "data": {
        "category": "Electronics",
        "extraProperty": "extraValue"
      }
    }
  ]
}