{
  "description": "sample Github_easy/o81581.json",
  "meta": {
    "full_size": 322,
    "stripped_size": 322,
    "features": [
      "additionalProperties",
      "patternProperties"
    ],
    "raw_features": [
      "$schema",
      "_boolSchema",
      "properties",
      "required",
      "type",
      "type:object",
      "type:string"
    ]
  },
  "schema": {
    "$schema": "http://json-schema.org/draft-04/schema#",
    "type": "object",
    "properties": {
      "city": {
        "type": "string"
      },
      "state": {
        "type": "string"
      },
      "zip": {
        "type": "string"
      },
      "country": {
        "type": "string"
      }
    },
    "patternProperties": {
      "^line[1-3]$": {
        "type": "string"
      }
    },
    "additionalProperties": false,
    "required": [
      "city",
      "state",
      "zip",
      "country",
      "line1"
    ]
  },
  "tests": [
    {
      "description": "llama 70b generated positive",
      "valid": true,
      "data": {
        "city": "New York",
        "state": "New York",
        "zip": "10001",
        "country": "USA",
        "line1": "123 Main St",
        "line2": "Apt 101",
        "line3": "Near Central Park"
      }
    },
    {
      "description": "llama 70b generated positive",
      "valid": true,
      "data": {
        "city": "New York",
        "state": "NY",
        "zip": "10001",
        "country": "USA",
        "line1": "123 Main St",
        "line2": "Apt 101",
        "line3": "Near Central Park"
      }
    },
    {
      "description": "llama-70b generated negative; focus on patternProperties keyword",
      "valid": false,
      "rust_error": "Additional properties are not allowed ('line4' was unexpected)",
      "python_error": "'line4' does not match any of the regexes: '^line[1-3]$'\n\nFailed validating 'additionalProperties' in schema:\n    {'$schema': 'http://json-schema.org/draft-04/schema#',\n     'type': 'object',\n     'properties': {'city': {'type': 'string'},\n                    'state': {'type': 'string'},\n                    'zip': {'type': 'string'},\n                    'country': {'type': 'string'}},\n     'patternProperties': {'^line[1-3]$': {'type': 'string'}},\n     'additionalProperties': False,\n     'required': ['city', 'state', 'zip', 'country', 'line1']}\n\nOn instance:\n    {'city': 'New York',\n     'state': 'NY',\n     'zip': '10001',\n     'country': 'USA',\n     'line1': '123 Main St',\n     'line2': 'Apt 101',\n     'line3': 'Near Central Park',\n     'line4': 'Extra Line'}",
      "data": {
        "city": "New York",
        "state": "NY",
        "zip": "10001",
        "country": "USA",
        "line1": "123 Main St",
        "line2": "Apt 101",
        "line3": "Near Central Park",
        "line4": "Extra Line"
      }
    },
    {
      "description": "llama-70b generated negative",
      "valid": false,
      "rust_error": "Additional properties are not allowed ('line4' was unexpected)",
      "python_error": "'line4' does not match any of the regexes: '^line[1-3]$'\n\nFailed validating 'additionalProperties' in schema:\n    {'$schema': 'http://json-schema.org/draft-04/schema#',\n     'type': 'object',\n     'properties': {'city': {'type': 'string'},\n                    'state': {'type': 'string'},\n                    'zip': {'type': 'string'},\n                    'country': {'type': 'string'}},\n     'patternProperties': {'^line[1-3]$': {'type': 'string'}},\n     'additionalProperties': False,\n     'required': ['city', 'state', 'zip', 'country', 'line1']}\n\nOn instance:\n    {'city': 'New York',\n     'state': 'NY',\n     'zip': '10001',\n     'country': 'USA',\n     'line1': '123 Main St',\n     'line2': 'Apt 101',\n     'line3': 'Near Central Park',\n     'line4': 'Extra Address Info'}",
      "data": {
        "city": "New York",
        "state": "NY",
        "zip": "10001",
        "country": "USA",
        "line1": "123 Main St",
        "line2": "Apt 101",
        "line3": "Near Central Park",
        "line4": "Extra Address Info"
      }
    }
  ]
}