{
  "description": "sample Snowplow/sp_295_Normalized.json",
  "meta": {
    "full_size": 446,
    "stripped_size": 289,
    "features": [
      "@minmaxLength",
      "additionalProperties",
      "items"
    ],
    "raw_features": [
      "_boolSchema",
      "minLength",
      "properties",
      "required",
      "type",
      "type:array",
      "type:object",
      "type:string"
    ]
  },
  "schema": {
    "additionalProperties": false,
    "description": "Schema for a link click event",
    "properties": {
      "elementClasses": {
        "items": {
          "type": "string"
        },
        "type": "array"
      },
      "elementContent": {
        "type": "string"
      },
      "elementId": {
        "type": "string"
      },
      "elementTarget": {
        "type": "string"
      },
      "targetUrl": {
        "minLength": 1,
        "type": "string"
      }
    },
    "required": [
      "targetUrl"
    ],
    "self": {
      "format": "jsonschema",
      "name": "link_click",
      "vendor": "com.snowplowanalytics.snowplow",
      "version": "1-0-1"
    },
    "type": "object"
  },
  "tests": [
    {
      "description": "llama 70b generated valid",
      "valid": true,
      "data": {
        "elementClasses": [
          "class1",
          "class2"
        ],
        "elementContent": "Link Content",
        "elementId": "link-id",
        "elementTarget": "_blank",
        "targetUrl": "https://www.example.com"
      }
    },
    {
      "description": "llama-70b generated negative; focus on minLength keyword",
      "valid": false,
      "rust_error": "\"\" is shorter than 1 character",
      "python_error": "'' should be non-empty\n\nFailed validating 'minLength' in schema['properties']['targetUrl']:\n    {'minLength': 1, 'type': 'string'}\n\nOn instance['targetUrl']:\n    ''",
      "data": {
        "elementClasses": [
          "class1",
          "class2"
        ],
        "elementContent": "Link Content",
        "elementId": "link-id",
        "elementTarget": "_blank",
        "targetUrl": ""
      }
    },
    {
      "description": "llama-70b generated negative",
      "valid": false,
      "rust_error": "\"\" is shorter than 1 character",
      "python_error": "Additional properties are not allowed ('extraProperty' was unexpected)\n\nFailed validating 'additionalProperties' in schema:\n    {'additionalProperties': False,\n     'description': 'Schema for a link click event',\n     'properties': {'elementClasses': {'items': {'type': 'string'},\n                                       'type': 'array'},\n                    'elementContent': {'type': 'string'},\n                    'elementId': {'type': 'string'},\n                    'elementTarget': {'type': 'string'},\n                    'targetUrl': {'minLength': 1, 'type': 'string'}},\n     'required': ['targetUrl'],\n     'self': {'format': 'jsonschema',\n              'name': 'link_click',\n              'vendor': 'com.snowplowanalytics.snowplow',\n              'version': '1-0-1'},\n     'type': 'object'}\n\nOn instance:\n    {'elementClasses': ['class1', 'class2'],\n     'elementContent': 'Link Content',\n     'elementId': 'link-id',\n     'elementTarget': '_blank',\n     'targetUrl': '',\n     'extraProperty': 'extraValue'}",
      "data": {
        "elementClasses": [
          "class1",
          "class2"
        ],
        "elementContent": "Link Content",
        "elementId": "link-id",
        "elementTarget": "_blank",
        "targetUrl": "",
        "extraProperty": "extraValue"
      }
    },
    {
      "description": "llama-70b generated negative",
      "valid": false,
      "rust_error": "123 is not of type \"string\"",
      "python_error": "Additional properties are not allowed ('extraProperty' was unexpected)\n\nFailed validating 'additionalProperties' in schema:\n    {'additionalProperties': False,\n     'description': 'Schema for a link click event',\n     'properties': {'elementClasses': {'items': {'type': 'string'},\n                                       'type': 'array'},\n                    'elementContent': {'type': 'string'},\n                    'elementId': {'type': 'string'},\n                    'elementTarget': {'type': 'string'},\n                    'targetUrl': {'minLength': 1, 'type': 'string'}},\n     'required': ['targetUrl'],\n     'self': {'format': 'jsonschema',\n              'name': 'link_click',\n              'vendor': 'com.snowplowanalytics.snowplow',\n              'version': '1-0-1'},\n     'type': 'object'}\n\nOn instance:\n    {'elementClasses': ['class1', 123],\n     'elementContent': 'Link Content',\n     'elementId': 'link-id',\n     'elementTarget': '_blank',\n     'targetUrl': 'https://www.example.com',\n     'extraProperty': 'extraValue'}",
      "data": {
        "elementClasses": [
          "class1",
          123
        ],
        "elementContent": "Link Content",
        "elementId": "link-id",
        "elementTarget": "_blank",
        "targetUrl": "https://www.example.com",
        "extraProperty": "extraValue"
      }
    },
    {
      "description": "llama-70b generated negative",
      "valid": false,
      "rust_error": "123 is not of type \"string\"",
      "python_error": "Additional properties are not allowed ('extraProperty' was unexpected)\n\nFailed validating 'additionalProperties' in schema:\n    {'additionalProperties': False,\n     'description': 'Schema for a link click event',\n     'properties': {'elementClasses': {'items': {'type': 'string'},\n                                       'type': 'array'},\n                    'elementContent': {'type': 'string'},\n                    'elementId': {'type': 'string'},\n                    'elementTarget': {'type': 'string'},\n                    'targetUrl': {'minLength': 1, 'type': 'string'}},\n     'required': ['targetUrl'],\n     'self': {'format': 'jsonschema',\n              'name': 'link_click',\n              'vendor': 'com.snowplowanalytics.snowplow',\n              'version': '1-0-1'},\n     'type': 'object'}\n\nOn instance:\n    {'elementClasses': ['class1', 123],\n     'elementContent': 'Link Content',\n     'elementId': 'link-id',\n     'elementTarget': '_blank',\n     'targetUrl': 'https://www.example.com',\n     'extraProperty': 'invalid'}",
      "data": {
        "elementClasses": [
          "class1",
          123
        ],
        "elementContent": "Link Content",
        "elementId": "link-id",
        "elementTarget": "_blank",
        "targetUrl": "https://www.example.com",
        "extraProperty": "invalid"
      }
    }
  ]
}