{
  "description": "sample Snowplow/sp_58_Normalized.json",
  "meta": {
    "full_size": 460,
    "stripped_size": 256,
    "features": [
      "@minmaxInteger",
      "additionalProperties"
    ],
    "raw_features": [
      "_boolSchema",
      "maximum",
      "minimum",
      "properties",
      "type",
      "type:[]",
      "type:integer",
      "type:null",
      "type:object",
      "type:string"
    ]
  },
  "schema": {
    "additionalProperties": false,
    "description": "Schema for a Google Analytics enhanced e-commerce promotion entity",
    "properties": {
      "creative": {
        "type": [
          "string",
          "null"
        ]
      },
      "id": {
        "type": [
          "string",
          "null"
        ]
      },
      "index": {
        "maximum": 200,
        "minimum": 1,
        "type": "integer"
      },
      "name": {
        "type": [
          "string",
          "null"
        ]
      },
      "position": {
        "type": [
          "string",
          "null"
        ]
      }
    },
    "self": {
      "format": "jsonschema",
      "name": "promotion",
      "vendor": "com.google.analytics.measurement-protocol",
      "version": "1-0-0"
    },
    "type": "object"
  },
  "tests": [
    {
      "description": "llama 70b generated valid",
      "valid": true,
      "data": {
        "creative": "Summer Sale",
        "id": "summer-sale-2023",
        "index": 1,
        "name": "Summer Sale Promotion",
        "position": "top-banner"
      }
    },
    {
      "description": "llama-70b generated negative; focus on type keyword with an array of types",
      "valid": false,
      "rust_error": "123 is not of types \"null\", \"string\"",
      "python_error": "123 is not of type 'string', 'null'\n\nFailed validating 'type' in schema['properties']['creative']:\n    {'type': ['string', 'null']}\n\nOn instance['creative']:\n    123",
      "data": {
        "creative": 123,
        "id": "summer-sale-2023",
        "index": 1,
        "name": "Summer Sale Promotion",
        "position": "top-banner"
      }
    },
    {
      "description": "llama-70b generated negative; focus on minimum keyword or maximum keyword",
      "valid": false,
      "rust_error": "201 is greater than the maximum of 200",
      "python_error": "201 is greater than the maximum of 200\n\nFailed validating 'maximum' in schema['properties']['index']:\n    {'maximum': 200, 'minimum': 1, 'type': 'integer'}\n\nOn instance['index']:\n    201",
      "data": {
        "creative": "Summer Sale",
        "id": "summer-sale-2023",
        "index": 201,
        "name": "Summer Sale Promotion",
        "position": "top-banner"
      }
    },
    {
      "description": "llama-70b generated negative",
      "valid": false,
      "rust_error": "201 is greater than the maximum of 200",
      "python_error": "Additional properties are not allowed ('extraProperty' was unexpected)\n\nFailed validating 'additionalProperties' in schema:\n    {'additionalProperties': False,\n     'description': 'Schema for a Google Analytics enhanced e-commerce '\n                    'promotion entity',\n     'properties': {'creative': {'type': ['string', 'null']},\n                    'id': {'type': ['string', 'null']},\n                    'index': {'maximum': 200,\n                              'minimum': 1,\n                              'type': 'integer'},\n                    'name': {'type': ['string', 'null']},\n                    'position': {'type': ['string', 'null']}},\n     'self': {'format': 'jsonschema',\n              'name': 'promotion',\n              'vendor': 'com.google.analytics.measurement-protocol',\n              'version': '1-0-0'},\n     'type': 'object'}\n\nOn instance:\n    {'creative': 'Summer Sale',\n     'id': 'summer-sale-2023',\n     'index': 201,\n     'name': 'Summer Sale Promotion',\n     'position': 'top-banner',\n     'extraProperty': 'Invalid'}",
      "data": {
        "creative": "Summer Sale",
        "id": "summer-sale-2023",
        "index": 201,
        "name": "Summer Sale Promotion",
        "position": "top-banner",
        "extraProperty": "Invalid"
      }
    },
    {
      "description": "llama-70b generated negative; focus on minimum keyword or maximum keyword",
      "valid": false,
      "rust_error": "0 is less than the minimum of 1",
      "python_error": "0 is less than the minimum of 1\n\nFailed validating 'minimum' in schema['properties']['index']:\n    {'maximum': 200, 'minimum': 1, 'type': 'integer'}\n\nOn instance['index']:\n    0",
      "data": {
        "creative": "Summer Sale",
        "id": "summer-sale-2023",
        "index": 0,
        "name": "Summer Sale Promotion",
        "position": "top-banner"
      }
    },
    {
      "description": "llama 70b generated positive",
      "valid": true,
      "data": {
        "creative": "Summer Sale",
        "id": "PROMO123",
        "index": 1,
        "name": "Summer Sale Promotion",
        "position": "top"
      }
    },
    {
      "description": "llama-70b generated negative; focus on type keyword with an array of types",
      "valid": false,
      "rust_error": "true is not of types \"null\", \"string\"",
      "python_error": "True is not of type 'string', 'null'\n\nFailed validating 'type' in schema['properties']['creative']:\n    {'type': ['string', 'null']}\n\nOn instance['creative']:\n    True",
      "data": {
        "creative": true,
        "id": "PROMO123",
        "index": 1,
        "name": "Summer Sale Promotion",
        "position": "top"
      }
    },
    {
      "description": "llama-70b generated negative; focus on minimum keyword or maximum keyword",
      "valid": false,
      "rust_error": "0 is less than the minimum of 1",
      "python_error": "0 is less than the minimum of 1\n\nFailed validating 'minimum' in schema['properties']['index']:\n    {'maximum': 200, 'minimum': 1, 'type': 'integer'}\n\nOn instance['index']:\n    0",
      "data": {
        "creative": "Summer Sale",
        "id": "PROMO123",
        "index": 0,
        "name": "Summer Sale Promotion",
        "position": "top"
      }
    },
    {
      "description": "llama-70b generated negative",
      "valid": false,
      "rust_error": "201 is greater than the maximum of 200",
      "python_error": "Additional properties are not allowed ('extraProperty' was unexpected)\n\nFailed validating 'additionalProperties' in schema:\n    {'additionalProperties': False,\n     'description': 'Schema for a Google Analytics enhanced e-commerce '\n                    'promotion entity',\n     'properties': {'creative': {'type': ['string', 'null']},\n                    'id': {'type': ['string', 'null']},\n                    'index': {'maximum': 200,\n                              'minimum': 1,\n                              'type': 'integer'},\n                    'name': {'type': ['string', 'null']},\n                    'position': {'type': ['string', 'null']}},\n     'self': {'format': 'jsonschema',\n              'name': 'promotion',\n              'vendor': 'com.google.analytics.measurement-protocol',\n              'version': '1-0-0'},\n     'type': 'object'}\n\nOn instance:\n    {'creative': 'Summer Sale',\n     'id': 'PROMO123',\n     'index': 201,\n     'name': 'Summer Sale Promotion',\n     'position': 'top',\n     'extraProperty': 'Invalid'}",
      "data": {
        "creative": "Summer Sale",
        "id": "PROMO123",
        "index": 201,
        "name": "Summer Sale Promotion",
        "position": "top",
        "extraProperty": "Invalid"
      }
    }
  ]
}