{
  "description": "sample Snowplow/sp_262_Normalized.json",
  "meta": {
    "full_size": 337,
    "stripped_size": 180,
    "features": [
      "@minmaxItems",
      "additionalProperties",
      "items"
    ],
    "raw_features": [
      "_boolSchema",
      "minItems",
      "properties",
      "required",
      "type",
      "type:array",
      "type:object",
      "type:string"
    ]
  },
  "schema": {
    "additionalProperties": false,
    "description": "Schema for a bad raw event",
    "properties": {
      "errors": {
        "items": {
          "type": "string"
        },
        "minItems": 1,
        "type": "array"
      },
      "line": {
        "type": "string"
      }
    },
    "required": [
      "line",
      "errors"
    ],
    "self": {
      "format": "jsonschema",
      "name": "bad_raw_event",
      "vendor": "com.snowplowanalytics.snowplow",
      "version": "1-0-0"
    },
    "type": "object"
  },
  "tests": [
    {
      "description": "llama 70b generated valid",
      "valid": true,
      "data": {
        "errors": [
          "Invalid JSON format",
          "Missing required field"
        ],
        "line": "{\"event\":\"page_view\",\"page\":\"home\"}"
      }
    },
    {
      "description": "llama-70b generated negative; focus on minItems keyword",
      "valid": false,
      "rust_error": "[] has less than 1 item",
      "python_error": "[] should be non-empty\n\nFailed validating 'minItems' in schema['properties']['errors']:\n    {'items': {'type': 'string'}, 'minItems': 1, 'type': 'array'}\n\nOn instance['errors']:\n    []",
      "data": {
        "errors": [],
        "line": "{\"event\":\"page_view\",\"page\":\"home\"}"
      }
    },
    {
      "description": "llama-70b generated negative",
      "valid": false,
      "rust_error": "Additional properties are not allowed ('extraField' was unexpected)",
      "python_error": "Additional properties are not allowed ('extraField' was unexpected)\n\nFailed validating 'additionalProperties' in schema:\n    {'additionalProperties': False,\n     'description': 'Schema for a bad raw event',\n     'properties': {'errors': {'items': {'type': 'string'},\n                               'minItems': 1,\n                               'type': 'array'},\n                    'line': {'type': 'string'}},\n     'required': ['line', 'errors'],\n     'self': {'format': 'jsonschema',\n              'name': 'bad_raw_event',\n              'vendor': 'com.snowplowanalytics.snowplow',\n              'version': '1-0-0'},\n     'type': 'object'}\n\nOn instance:\n    {'errors': ['Invalid JSON format', 'Missing required field'],\n     'line': '{\"event\":\"page_view\",\"page\":\"home\"}',\n     'extraField': 'This is an extra field'}",
      "data": {
        "errors": [
          "Invalid JSON format",
          "Missing required field"
        ],
        "line": "{\"event\":\"page_view\",\"page\":\"home\"}",
        "extraField": "This is an extra field"
      }
    },
    {
      "description": "llama-70b generated negative",
      "valid": false,
      "rust_error": "Additional properties are not allowed ('extra' was unexpected)",
      "python_error": "Additional properties are not allowed ('extra' was unexpected)\n\nFailed validating 'additionalProperties' in schema:\n    {'additionalProperties': False,\n     'description': 'Schema for a bad raw event',\n     'properties': {'errors': {'items': {'type': 'string'},\n                               'minItems': 1,\n                               'type': 'array'},\n                    'line': {'type': 'string'}},\n     'required': ['line', 'errors'],\n     'self': {'format': 'jsonschema',\n              'name': 'bad_raw_event',\n              'vendor': 'com.snowplowanalytics.snowplow',\n              'version': '1-0-0'},\n     'type': 'object'}\n\nOn instance:\n    {'errors': ['Invalid JSON format'],\n     'line': '{\"event\":\"page_view\",\"page\":\"home\"}',\n     'extra': 'this is an extra property'}",
      "data": {
        "errors": [
          "Invalid JSON format"
        ],
        "line": "{\"event\":\"page_view\",\"page\":\"home\"}",
        "extra": "this is an extra property"
      }
    },
    {
      "description": "llama 70b generated positive",
      "valid": true,
      "data": {
        "errors": [
          "Error 1: Invalid data",
          "Error 2: Missing field"
        ],
        "line": "This is a raw event line"
      }
    },
    {
      "description": "llama-70b generated negative; focus on minItems keyword",
      "valid": false,
      "rust_error": "[] has less than 1 item",
      "python_error": "[] should be non-empty\n\nFailed validating 'minItems' in schema['properties']['errors']:\n    {'items': {'type': 'string'}, 'minItems': 1, 'type': 'array'}\n\nOn instance['errors']:\n    []",
      "data": {
        "errors": [],
        "line": "This is a raw event line"
      }
    },
    {
      "description": "llama-70b generated negative",
      "valid": false,
      "rust_error": "Additional properties are not allowed ('extraProperty' was unexpected)",
      "python_error": "Additional properties are not allowed ('extraProperty' was unexpected)\n\nFailed validating 'additionalProperties' in schema:\n    {'additionalProperties': False,\n     'description': 'Schema for a bad raw event',\n     'properties': {'errors': {'items': {'type': 'string'},\n                               'minItems': 1,\n                               'type': 'array'},\n                    'line': {'type': 'string'}},\n     'required': ['line', 'errors'],\n     'self': {'format': 'jsonschema',\n              'name': 'bad_raw_event',\n              'vendor': 'com.snowplowanalytics.snowplow',\n              'version': '1-0-0'},\n     'type': 'object'}\n\nOn instance:\n    {'line': '',\n     'errors': ['Error 1: Invalid data'],\n     'extraProperty': 'Extra property added'}",
      "data": {
        "line": "",
        "errors": [
          "Error 1: Invalid data"
        ],
        "extraProperty": "Extra property added"
      }
    }
  ]
}