{
  "description": "sample Snowplow/sp_168_Normalized.json",
  "meta": {
    "full_size": 396,
    "stripped_size": 206,
    "features": [
      "additionalProperties"
    ],
    "raw_features": [
      "_boolSchema",
      "properties",
      "type",
      "type:integer",
      "type:object",
      "type:string"
    ]
  },
  "schema": {
    "additionalProperties": false,
    "description": "Schema for a Pingdom incident assigned event with a user being notified",
    "properties": {
      "check": {
        "type": "string"
      },
      "checkname": {
        "type": "string"
      },
      "description": {
        "type": "string"
      },
      "host": {
        "type": "string"
      },
      "incidentid": {
        "type": "integer"
      }
    },
    "self": {
      "format": "jsonschema",
      "name": "incident_notify_user",
      "vendor": "com.pingdom",
      "version": "1-0-0"
    },
    "type": "object"
  },
  "tests": [
    {
      "description": "llama 70b generated valid",
      "valid": true,
      "data": {
        "check": "http",
        "checkname": "My Website",
        "description": "My website is down",
        "host": "example.com",
        "incidentid": 12345
      }
    },
    {
      "description": "llama-70b generated negative",
      "valid": false,
      "rust_error": "Additional properties are not allowed ('extra' was unexpected)",
      "python_error": "Additional properties are not allowed ('extra' was unexpected)\n\nFailed validating 'additionalProperties' in schema:\n    {'additionalProperties': False,\n     'description': 'Schema for a Pingdom incident assigned event with a '\n                    'user being notified',\n     'properties': {'check': {'type': 'string'},\n                    'checkname': {'type': 'string'},\n                    'description': {'type': 'string'},\n                    'host': {'type': 'string'},\n                    'incidentid': {'type': 'integer'}},\n     'self': {'format': 'jsonschema',\n              'name': 'incident_notify_user',\n              'vendor': 'com.pingdom',\n              'version': '1-0-0'},\n     'type': 'object'}\n\nOn instance:\n    {'check': 'http',\n     'checkname': 'My Website',\n     'description': 'My website is down',\n     'host': 'example.com',\n     'incidentid': 12345,\n     'extra': 'field'}",
      "data": {
        "check": "http",
        "checkname": "My Website",
        "description": "My website is down",
        "host": "example.com",
        "incidentid": 12345,
        "extra": "field"
      }
    },
    {
      "description": "llama-70b generated negative",
      "valid": false,
      "rust_error": "Additional properties are not allowed ('extra_property' was unexpected)",
      "python_error": "Additional properties are not allowed ('extra_property' was unexpected)\n\nFailed validating 'additionalProperties' in schema:\n    {'additionalProperties': False,\n     'description': 'Schema for a Pingdom incident assigned event with a '\n                    'user being notified',\n     'properties': {'check': {'type': 'string'},\n                    'checkname': {'type': 'string'},\n                    'description': {'type': 'string'},\n                    'host': {'type': 'string'},\n                    'incidentid': {'type': 'integer'}},\n     'self': {'format': 'jsonschema',\n              'name': 'incident_notify_user',\n              'vendor': 'com.pingdom',\n              'version': '1-0-0'},\n     'type': 'object'}\n\nOn instance:\n    {'check': 'http',\n     'checkname': 'My Website',\n     'description': 'My website is down',\n     'host': 'example.com',\n     'incidentid': 12345,\n     'extra_property': 'extra_value'}",
      "data": {
        "check": "http",
        "checkname": "My Website",
        "description": "My website is down",
        "host": "example.com",
        "incidentid": 12345,
        "extra_property": "extra_value"
      }
    },
    {
      "description": "llama-70b generated negative",
      "valid": false,
      "rust_error": "Additional properties are not allowed ('extra' was unexpected)",
      "python_error": "Additional properties are not allowed ('extra' was unexpected)\n\nFailed validating 'additionalProperties' in schema:\n    {'additionalProperties': False,\n     'description': 'Schema for a Pingdom incident assigned event with a '\n                    'user being notified',\n     'properties': {'check': {'type': 'string'},\n                    'checkname': {'type': 'string'},\n                    'description': {'type': 'string'},\n                    'host': {'type': 'string'},\n                    'incidentid': {'type': 'integer'}},\n     'self': {'format': 'jsonschema',\n              'name': 'incident_notify_user',\n              'vendor': 'com.pingdom',\n              'version': '1-0-0'},\n     'type': 'object'}\n\nOn instance:\n    {'check': 'http',\n     'checkname': 'My Website',\n     'description': 'My website is down',\n     'host': 'example.com',\n     'incidentid': 12345,\n     'extra': 'invalid property'}",
      "data": {
        "check": "http",
        "checkname": "My Website",
        "description": "My website is down",
        "host": "example.com",
        "incidentid": 12345,
        "extra": "invalid property"
      }
    }
  ]
}