{
  "description": "sample Snowplow/sp_38_Normalized.json",
  "meta": {
    "full_size": 441,
    "stripped_size": 269,
    "features": [
      "@minmaxLength",
      "additionalProperties"
    ],
    "raw_features": [
      "_boolSchema",
      "maxLength",
      "properties",
      "type",
      "type:[]",
      "type:null",
      "type:object",
      "type:string"
    ]
  },
  "schema": {
    "additionalProperties": false,
    "description": "Schema for a Google Analytics app entity",
    "properties": {
      "id": {
        "maxLength": 150,
        "type": [
          "string",
          "null"
        ]
      },
      "installerId": {
        "maxLength": 150,
        "type": [
          "string",
          "null"
        ]
      },
      "name": {
        "maxLength": 100,
        "type": [
          "string",
          "null"
        ]
      },
      "version": {
        "maxLength": 100,
        "type": [
          "string",
          "null"
        ]
      }
    },
    "self": {
      "format": "jsonschema",
      "name": "app",
      "vendor": "com.google.analytics.measurement-protocol",
      "version": "1-0-0"
    },
    "type": "object"
  },
  "tests": [
    {
      "description": "llama 70b generated valid",
      "valid": true,
      "data": {
        "id": "example-id",
        "installerId": "example-installer-id",
        "name": "Example App",
        "version": "1.0.0"
      }
    },
    {
      "description": "llama-70b generated negative; focus on type keyword with an array of types",
      "valid": false,
      "rust_error": "123 is not of types \"null\", \"string\"",
      "python_error": "123 is not of type 'string', 'null'\n\nFailed validating 'type' in schema['properties']['id']:\n    {'maxLength': 150, 'type': ['string', 'null']}\n\nOn instance['id']:\n    123",
      "data": {
        "id": 123,
        "installerId": "example-installer-id",
        "name": "Example App",
        "version": "1.0.0"
      }
    },
    {
      "description": "llama-70b generated negative",
      "valid": false,
      "rust_error": "Additional properties are not allowed ('extraProperty' was unexpected)",
      "python_error": "Additional properties are not allowed ('extraProperty' was unexpected)\n\nFailed validating 'additionalProperties' in schema:\n    {'additionalProperties': False,\n     'description': 'Schema for a Google Analytics app entity',\n     'properties': {'id': {'maxLength': 150, 'type': ['string', 'null']},\n                    'installerId': {'maxLength': 150,\n                                    'type': ['string', 'null']},\n                    'name': {'maxLength': 100, 'type': ['string', 'null']},\n                    'version': {'maxLength': 100,\n                                'type': ['string', 'null']}},\n     'self': {'format': 'jsonschema',\n              'name': 'app',\n              'vendor': 'com.google.analytics.measurement-protocol',\n              'version': '1-0-0'},\n     'type': 'object'}\n\nOn instance:\n    {'id': 'example-id',\n     'installerId': 'example-installer-id',\n     'name': 'Example App',\n     'version': '1.0.0',\n     'extraProperty': 'extraValue'}",
      "data": {
        "id": "example-id",
        "installerId": "example-installer-id",
        "name": "Example App",
        "version": "1.0.0",
        "extraProperty": "extraValue"
      }
    },
    {
      "description": "llama 70b generated positive",
      "valid": true,
      "data": {
        "id": "example-id-123",
        "installerId": "example-installer-id-456",
        "name": "Example App",
        "version": "1.2.3"
      }
    },
    {
      "description": "llama-70b generated negative; focus on type keyword with an array of types",
      "valid": false,
      "rust_error": "true is not of types \"null\", \"string\"",
      "python_error": "True is not of type 'string', 'null'\n\nFailed validating 'type' in schema['properties']['id']:\n    {'maxLength': 150, 'type': ['string', 'null']}\n\nOn instance['id']:\n    True",
      "data": {
        "id": true,
        "installerId": "example-installer-id-456",
        "name": "Example App",
        "version": "1.2.3"
      }
    },
    {
      "description": "llama-70b generated negative; focus on maxLength keyword",
      "valid": false,
      "rust_error": "Additional properties are not allowed ('extraProperty' was unexpected)",
      "python_error": "Additional properties are not allowed ('extraProperty' was unexpected)\n\nFailed validating 'additionalProperties' in schema:\n    {'additionalProperties': False,\n     'description': 'Schema for a Google Analytics app entity',\n     'properties': {'id': {'maxLength': 150, 'type': ['string', 'null']},\n                    'installerId': {'maxLength': 150,\n                                    'type': ['string', 'null']},\n                    'name': {'maxLength': 100, 'type': ['string', 'null']},\n                    'version': {'maxLength': 100,\n                                'type': ['string', 'null']}},\n     'self': {'format': 'jsonschema',\n              'name': 'app',\n              'vendor': 'com.google.analytics.measurement-protocol',\n              'version': '1-0-0'},\n     'type': 'object'}\n\nOn instance:\n    {'id': 'example-id-123',\n     'installerId': 'example-installer-id-456',\n     'name': 'Example App',\n     'version': '1.2.3',\n     'extraProperty': 'invalid'}",
      "data": {
        "id": "example-id-123",
        "installerId": "example-installer-id-456",
        "name": "Example App",
        "version": "1.2.3",
        "extraProperty": "invalid"
      }
    },
    {
      "description": "llama-70b generated negative",
      "valid": false,
      "rust_error": "Additional properties are not allowed ('extraProperty' was unexpected)",
      "python_error": "Additional properties are not allowed ('extraProperty' was unexpected)\n\nFailed validating 'additionalProperties' in schema:\n    {'additionalProperties': False,\n     'description': 'Schema for a Google Analytics app entity',\n     'properties': {'id': {'maxLength': 150, 'type': ['string', 'null']},\n                    'installerId': {'maxLength': 150,\n                                    'type': ['string', 'null']},\n                    'name': {'maxLength': 100, 'type': ['string', 'null']},\n                    'version': {'maxLength': 100,\n                                'type': ['string', 'null']}},\n     'self': {'format': 'jsonschema',\n              'name': 'app',\n              'vendor': 'com.google.analytics.measurement-protocol',\n              'version': '1-0-0'},\n     'type': 'object'}\n\nOn instance:\n    {'id': 'example-id-123',\n     'installerId': 'example-installer-id-456',\n     'name': 'Example App',\n     'version': '1.2.3',\n     'extraProperty': 'extraValue'}",
      "data": {
        "id": "example-id-123",
        "installerId": "example-installer-id-456",
        "name": "Example App",
        "version": "1.2.3",
        "extraProperty": "extraValue"
      }
    }
  ]
}