{
  "description": "sample Snowplow/sp_242_Normalized.json",
  "meta": {
    "full_size": 422,
    "stripped_size": 242,
    "features": [
      "additionalProperties"
    ],
    "raw_features": [
      "_boolSchema",
      "properties",
      "type",
      "type:number",
      "type:object",
      "type:string"
    ]
  },
  "schema": {
    "additionalProperties": false,
    "description": "Schema for a stream write failure",
    "properties": {
      "appName": {
        "type": "string"
      },
      "errorMessage": {
        "type": "string"
      },
      "errorType": {
        "type": "string"
      },
      "putSize": {
        "type": "number"
      },
      "retryCount": {
        "type": "number"
      },
      "streamName": {
        "type": "string"
      }
    },
    "self": {
      "format": "jsonschema",
      "name": "stream_write_failed",
      "vendor": "com.snowplowanalytics.monitoring.kinesis",
      "version": "1-0-0"
    },
    "type": "object"
  },
  "tests": [
    {
      "description": "llama 70b generated valid",
      "valid": true,
      "data": {
        "appName": "My App",
        "errorMessage": "Failed to write to stream",
        "errorType": "IOException",
        "putSize": 1024,
        "retryCount": 3,
        "streamName": "my_stream"
      }
    },
    {
      "description": "llama-70b generated negative",
      "valid": false,
      "rust_error": "Additional properties are not allowed ('extraProperty' was unexpected)",
      "python_error": "Additional properties are not allowed ('extraProperty' was unexpected)\n\nFailed validating 'additionalProperties' in schema:\n    {'additionalProperties': False,\n     'description': 'Schema for a stream write failure',\n     'properties': {'appName': {'type': 'string'},\n                    'errorMessage': {'type': 'string'},\n                    'errorType': {'type': 'string'},\n                    'putSize': {'type': 'number'},\n                    'retryCount': {'type': 'number'},\n                    'streamName': {'type': 'string'}},\n     'self': {'format': 'jsonschema',\n              'name': 'stream_write_failed',\n              'vendor': 'com.snowplowanalytics.monitoring.kinesis',\n              'version': '1-0-0'},\n     'type': 'object'}\n\nOn instance:\n    {'appName': 'My App',\n     'errorMessage': 'Failed to write to stream',\n     'errorType': 'IOException',\n     'putSize': 1024,\n     'retryCount': 3,\n     'streamName': 'my_stream',\n     'extraProperty': 'Invalid'}",
      "data": {
        "appName": "My App",
        "errorMessage": "Failed to write to stream",
        "errorType": "IOException",
        "putSize": 1024,
        "retryCount": 3,
        "streamName": "my_stream",
        "extraProperty": "Invalid"
      }
    },
    {
      "description": "llama 70b generated positive",
      "valid": true,
      "data": {
        "appName": "My Kinesis App",
        "errorMessage": "Failed to write to stream",
        "errorType": "KinesisException",
        "putSize": 1024,
        "retryCount": 3,
        "streamName": "my-kinesis-stream"
      }
    },
    {
      "description": "llama-70b generated negative",
      "valid": false,
      "rust_error": "\"3\" is not of type \"number\"",
      "python_error": "Additional properties are not allowed ('extra key removed', 'overidden with string' were unexpected)\n\nFailed validating 'additionalProperties' in schema:\n    {'additionalProperties': False,\n     'description': 'Schema for a stream write failure',\n     'properties': {'appName': {'type': 'string'},\n                    'errorMessage': {'type': 'string'},\n                    'errorType': {'type': 'string'},\n                    'putSize': {'type': 'number'},\n                    'retryCount': {'type': 'number'},\n                    'streamName': {'type': 'string'}},\n     'self': {'format': 'jsonschema',\n              'name': 'stream_write_failed',\n              'vendor': 'com.snowplowanalytics.monitoring.kinesis',\n              'version': '1-0-0'},\n     'type': 'object'}\n\nOn instance:\n    {'appName': 'My Kinesis App',\n     'errorMessage': 'Failed to write to stream',\n     'errorType': 'KinesisException',\n     'putSize': 1024,\n     'retryCount': '3',\n     'overidden with string': 'streamName',\n     'extra key removed': 'my-stream'}",
      "data": {
        "appName": "My Kinesis App",
        "errorMessage": "Failed to write to stream",
        "errorType": "KinesisException",
        "putSize": 1024,
        "retryCount": "3",
        "overidden with string": "streamName",
        "extra key removed": "my-stream"
      }
    }
  ]
}