{
  "description": "sample Snowplow/sp_166_Normalized.json",
  "meta": {
    "full_size": 364,
    "stripped_size": 206,
    "features": [
      "additionalProperties"
    ],
    "raw_features": [
      "_boolSchema",
      "properties",
      "type",
      "type:integer",
      "type:object",
      "type:string"
    ]
  },
  "schema": {
    "additionalProperties": false,
    "description": "Schema for a Pingdom incident assigned event",
    "properties": {
      "check": {
        "type": "string"
      },
      "checkname": {
        "type": "string"
      },
      "description": {
        "type": "string"
      },
      "host": {
        "type": "string"
      },
      "incidentid": {
        "type": "integer"
      }
    },
    "self": {
      "format": "jsonschema",
      "name": "incident_assign",
      "vendor": "com.pingdom",
      "version": "1-0-0"
    },
    "type": "object"
  },
  "tests": [
    {
      "description": "llama 70b generated valid",
      "valid": true,
      "data": {
        "check": "12345",
        "checkname": "Example Check",
        "description": "This is an example incident assigned event",
        "host": "example.com",
        "incidentid": 1
      }
    },
    {
      "description": "llama-70b generated negative",
      "valid": false,
      "rust_error": "Additional properties are not allowed ('extra' was unexpected)",
      "python_error": "Additional properties are not allowed ('extra' was unexpected)\n\nFailed validating 'additionalProperties' in schema:\n    {'additionalProperties': False,\n     'description': 'Schema for a Pingdom incident assigned event',\n     'properties': {'check': {'type': 'string'},\n                    'checkname': {'type': 'string'},\n                    'description': {'type': 'string'},\n                    'host': {'type': 'string'},\n                    'incidentid': {'type': 'integer'}},\n     'self': {'format': 'jsonschema',\n              'name': 'incident_assign',\n              'vendor': 'com.pingdom',\n              'version': '1-0-0'},\n     'type': 'object'}\n\nOn instance:\n    {'check': '12345',\n     'checkname': 'Example Check',\n     'description': 'This is an example incident assigned event',\n     'host': 'example.com',\n     'incidentid': 1,\n     'extra': 'Invalid property'}",
      "data": {
        "check": "12345",
        "checkname": "Example Check",
        "description": "This is an example incident assigned event",
        "host": "example.com",
        "incidentid": 1,
        "extra": "Invalid property"
      }
    },
    {
      "description": "llama 70b generated positive",
      "valid": true,
      "data": {
        "check": "check-123",
        "checkname": "Example Check",
        "description": "This is an example incident assigned event.",
        "host": "example-host.com",
        "incidentid": 12345
      }
    },
    {
      "description": "llama-70b generated negative",
      "valid": false,
      "rust_error": "Additional properties are not allowed ('extraproperty' was unexpected)",
      "python_error": "Additional properties are not allowed ('extraproperty' was unexpected)\n\nFailed validating 'additionalProperties' in schema:\n    {'additionalProperties': False,\n     'description': 'Schema for a Pingdom incident assigned event',\n     'properties': {'check': {'type': 'string'},\n                    'checkname': {'type': 'string'},\n                    'description': {'type': 'string'},\n                    'host': {'type': 'string'},\n                    'incidentid': {'type': 'integer'}},\n     'self': {'format': 'jsonschema',\n              'name': 'incident_assign',\n              'vendor': 'com.pingdom',\n              'version': '1-0-0'},\n     'type': 'object'}\n\nOn instance:\n    {'check': 'check-123',\n     'checkname': 'Example Check',\n     'description': 'This is an example incident assigned event.',\n     'host': 'example-host.com',\n     'incidentid': 12345,\n     'extraproperty': 'value'}",
      "data": {
        "check": "check-123",
        "checkname": "Example Check",
        "description": "This is an example incident assigned event.",
        "host": "example-host.com",
        "incidentid": 12345,
        "extraproperty": "value"
      }
    }
  ]
}