{
  "description": "sample Snowplow/sp_275_Normalized.json",
  "meta": {
    "full_size": 701,
    "stripped_size": 499,
    "features": [
      "additionalProperties",
      "enum"
    ],
    "raw_features": [
      "_boolSchema",
      "properties",
      "required",
      "type",
      "type:boolean",
      "type:object",
      "type:string"
    ]
  },
  "schema": {
    "additionalProperties": false,
    "description": "Schema for configuration of currency-conversion enrichment",
    "properties": {
      "enabled": {
        "type": "boolean"
      },
      "name": {
        "type": "string"
      },
      "parameters": {
        "additionalProperties": false,
        "properties": {
          "accountType": {
            "enum": [
              "DEVELOPER",
              "ENTERPRISE",
              "UNLIMITED"
            ],
            "type": "string"
          },
          "apiKey": {
            "type": "string"
          },
          "baseCurrency": {
            "type": "string"
          },
          "rateAt": {
            "enum": [
              "EOD_PRIOR"
            ]
          }
        },
        "required": [
          "apiKey",
          "baseCurrency",
          "rateAt",
          "accountType"
        ],
        "type": "object"
      },
      "vendor": {
        "type": "string"
      }
    },
    "required": [
      "name",
      "vendor",
      "enabled",
      "parameters"
    ],
    "self": {
      "format": "jsonschema",
      "name": "currency_conversion_config",
      "vendor": "com.snowplowanalytics.snowplow",
      "version": "1-0-0"
    },
    "type": "object"
  },
  "tests": [
    {
      "description": "llama 70b generated valid",
      "valid": true,
      "data": {
        "enabled": true,
        "name": "Currency Conversion Enrichment",
        "parameters": {
          "accountType": "DEVELOPER",
          "apiKey": "your_api_key_here",
          "baseCurrency": "USD",
          "rateAt": "EOD_PRIOR"
        },
        "vendor": "Snowplow"
      }
    },
    {
      "description": "llama-70b generated negative",
      "valid": false,
      "rust_error": "Additional properties are not allowed ('extraParam' was unexpected)",
      "python_error": "Additional properties are not allowed ('extraParam' was unexpected)\n\nFailed validating 'additionalProperties' in schema['properties']['parameters']:\n    {'additionalProperties': False,\n     'properties': {'accountType': {'enum': ['DEVELOPER',\n                                             'ENTERPRISE',\n                                             'UNLIMITED'],\n                                    'type': 'string'},\n                    'apiKey': {'type': 'string'},\n                    'baseCurrency': {'type': 'string'},\n                    'rateAt': {'enum': ['EOD_PRIOR']}},\n     'required': ['apiKey', 'baseCurrency', 'rateAt', 'accountType'],\n     'type': 'object'}\n\nOn instance['parameters']:\n    {'accountType': 'DEVELOPER',\n     'apiKey': 'your_api_key_here',\n     'baseCurrency': 'USD',\n     'rateAt': 'EOD_PRIOR',\n     'extraParam': 'extraValue'}",
      "data": {
        "enabled": true,
        "name": "Currency Conversion Enrichment",
        "parameters": {
          "accountType": "DEVELOPER",
          "apiKey": "your_api_key_here",
          "baseCurrency": "USD",
          "rateAt": "EOD_PRIOR",
          "extraParam": "extraValue"
        },
        "vendor": "Snowplow"
      }
    },
    {
      "description": "llama-70b generated negative",
      "valid": false,
      "rust_error": "Additional properties are not allowed ('extraProperty' was unexpected)",
      "python_error": "Additional properties are not allowed ('extraProperty' was unexpected)\n\nFailed validating 'additionalProperties' in schema['properties']['parameters']:\n    {'additionalProperties': False,\n     'properties': {'accountType': {'enum': ['DEVELOPER',\n                                             'ENTERPRISE',\n                                             'UNLIMITED'],\n                                    'type': 'string'},\n                    'apiKey': {'type': 'string'},\n                    'baseCurrency': {'type': 'string'},\n                    'rateAt': {'enum': ['EOD_PRIOR']}},\n     'required': ['apiKey', 'baseCurrency', 'rateAt', 'accountType'],\n     'type': 'object'}\n\nOn instance['parameters']:\n    {'accountType': 'DEVELOPER',\n     'apiKey': 'your_api_key_here',\n     'baseCurrency': 'USD',\n     'rateAt': 'EOD_PRIOR',\n     'extraProperty': 'extraValue'}",
      "data": {
        "enabled": true,
        "name": "Currency Conversion Enrichment",
        "parameters": {
          "accountType": "DEVELOPER",
          "apiKey": "your_api_key_here",
          "baseCurrency": "USD",
          "rateAt": "EOD_PRIOR",
          "extraProperty": "extraValue"
        },
        "vendor": "Snowplow"
      }
    },
    {
      "description": "llama-70b generated negative",
      "valid": false,
      "rust_error": "Additional properties are not allowed ('extraParam' was unexpected)",
      "python_error": "Additional properties are not allowed ('extraParam' was unexpected)\n\nFailed validating 'additionalProperties' in schema['properties']['parameters']:\n    {'additionalProperties': False,\n     'properties': {'accountType': {'enum': ['DEVELOPER',\n                                             'ENTERPRISE',\n                                             'UNLIMITED'],\n                                    'type': 'string'},\n                    'apiKey': {'type': 'string'},\n                    'baseCurrency': {'type': 'string'},\n                    'rateAt': {'enum': ['EOD_PRIOR']}},\n     'required': ['apiKey', 'baseCurrency', 'rateAt', 'accountType'],\n     'type': 'object'}\n\nOn instance['parameters']:\n    {'accountType': 'DEVELOPER',\n     'apiKey': 'your_api_key_here',\n     'baseCurrency': 'USD',\n     'rateAt': 'EOD_PRIOR',\n     'extraParam': 'extra value'}",
      "data": {
        "enabled": true,
        "name": "Currency Conversion Enrichment",
        "parameters": {
          "accountType": "DEVELOPER",
          "apiKey": "your_api_key_here",
          "baseCurrency": "USD",
          "rateAt": "EOD_PRIOR",
          "extraParam": "extra value"
        },
        "vendor": "Snowplow"
      }
    }
  ]
}