{
  "description": "sample Snowplow/sp_320_Normalized.json",
  "meta": {
    "full_size": 370,
    "stripped_size": 216,
    "features": [
      "additionalProperties"
    ],
    "raw_features": [
      "_boolSchema",
      "properties",
      "required",
      "type",
      "type:number",
      "type:object",
      "type:string"
    ]
  },
  "schema": {
    "additionalProperties": false,
    "description": "Schema for a user timing event",
    "properties": {
      "category": {
        "type": "string"
      },
      "label": {
        "type": "string"
      },
      "timing": {
        "type": "number"
      },
      "variable": {
        "type": "string"
      }
    },
    "required": [
      "category",
      "variable",
      "timing"
    ],
    "self": {
      "format": "jsonschema",
      "name": "timing",
      "vendor": "com.snowplowanalytics.snowplow",
      "version": "1-0-0"
    },
    "type": "object"
  },
  "tests": [
    {
      "description": "llama 70b generated valid",
      "valid": true,
      "data": {
        "category": "performance",
        "label": "loading_time",
        "timing": 123.45,
        "variable": "page_load"
      }
    },
    {
      "description": "llama-70b generated negative",
      "valid": false,
      "rust_error": "\"123.45\" is not of type \"number\"",
      "python_error": "Additional properties are not allowed ('extra_property' was unexpected)\n\nFailed validating 'additionalProperties' in schema:\n    {'additionalProperties': False,\n     'description': 'Schema for a user timing event',\n     'properties': {'category': {'type': 'string'},\n                    'label': {'type': 'string'},\n                    'timing': {'type': 'number'},\n                    'variable': {'type': 'string'}},\n     'required': ['category', 'variable', 'timing'],\n     'self': {'format': 'jsonschema',\n              'name': 'timing',\n              'vendor': 'com.snowplowanalytics.snowplow',\n              'version': '1-0-0'},\n     'type': 'object'}\n\nOn instance:\n    {'category': 'performance',\n     'label': 'loading_time',\n     'timing': '123.45',\n     'variable': 'page_load',\n     'extra_property': 'invalid'}",
      "data": {
        "category": "performance",
        "label": "loading_time",
        "timing": "123.45",
        "variable": "page_load",
        "extra_property": "invalid"
      }
    },
    {
      "description": "llama 70b generated positive",
      "valid": true,
      "data": {
        "category": "user_interaction",
        "label": "submit_button",
        "timing": 123.45,
        "variable": "button_click"
      }
    },
    {
      "description": "llama-70b generated negative",
      "valid": false,
      "rust_error": "Additional properties are not allowed ('extra_property' was unexpected)",
      "python_error": "Additional properties are not allowed ('extra_property' was unexpected)\n\nFailed validating 'additionalProperties' in schema:\n    {'additionalProperties': False,\n     'description': 'Schema for a user timing event',\n     'properties': {'category': {'type': 'string'},\n                    'label': {'type': 'string'},\n                    'timing': {'type': 'number'},\n                    'variable': {'type': 'string'}},\n     'required': ['category', 'variable', 'timing'],\n     'self': {'format': 'jsonschema',\n              'name': 'timing',\n              'vendor': 'com.snowplowanalytics.snowplow',\n              'version': '1-0-0'},\n     'type': 'object'}\n\nOn instance:\n    {'category': 'user_interaction',\n     'variable': 'button_click',\n     'timing': 123.45,\n     'label': 'submit_button',\n     'extra_property': 'extra_value'}",
      "data": {
        "category": "user_interaction",
        "variable": "button_click",
        "timing": 123.45,
        "label": "submit_button",
        "extra_property": "extra_value"
      }
    }
  ]
}