{
  "description": "sample Snowplow/sp_250_Normalized.json",
  "meta": {
    "full_size": 417,
    "stripped_size": 257,
    "features": [
      "additionalProperties"
    ],
    "raw_features": [
      "_boolSchema",
      "properties",
      "required",
      "type",
      "type:number",
      "type:object",
      "type:string"
    ]
  },
  "schema": {
    "additionalProperties": false,
    "description": "Schema for an add-to-cart event",
    "properties": {
      "category": {
        "type": "string"
      },
      "currency": {
        "type": "string"
      },
      "name": {
        "type": "string"
      },
      "quantity": {
        "type": "number"
      },
      "sku": {
        "type": "string"
      },
      "unitPrice": {
        "type": "number"
      }
    },
    "required": [
      "sku",
      "quantity"
    ],
    "self": {
      "format": "jsonschema",
      "name": "add_to_cart",
      "vendor": "com.snowplowanalytics.snowplow",
      "version": "1-0-0"
    },
    "type": "object"
  },
  "tests": [
    {
      "description": "llama 70b generated valid",
      "valid": true,
      "data": {
        "category": "Electronics",
        "currency": "USD",
        "name": "Apple iPhone 14",
        "quantity": 1,
        "sku": "IPHONE14",
        "unitPrice": 999.99
      }
    },
    {
      "description": "llama-70b generated negative",
      "valid": false,
      "rust_error": "Additional properties are not allowed ('extraProperty' was unexpected)",
      "python_error": "Additional properties are not allowed ('extraProperty' was unexpected)\n\nFailed validating 'additionalProperties' in schema:\n    {'additionalProperties': False,\n     'description': 'Schema for an add-to-cart event',\n     'properties': {'category': {'type': 'string'},\n                    'currency': {'type': 'string'},\n                    'name': {'type': 'string'},\n                    'quantity': {'type': 'number'},\n                    'sku': {'type': 'string'},\n                    'unitPrice': {'type': 'number'}},\n     'required': ['sku', 'quantity'],\n     'self': {'format': 'jsonschema',\n              'name': 'add_to_cart',\n              'vendor': 'com.snowplowanalytics.snowplow',\n              'version': '1-0-0'},\n     'type': 'object'}\n\nOn instance:\n    {'category': 'Electronics',\n     'currency': 'USD',\n     'name': 'Apple iPhone 14',\n     'quantity': 1,\n     'sku': 'IPHONE14',\n     'unitPrice': 999.99,\n     'extraProperty': 'Invalid'}",
      "data": {
        "category": "Electronics",
        "currency": "USD",
        "name": "Apple iPhone 14",
        "quantity": 1,
        "sku": "IPHONE14",
        "unitPrice": 999.99,
        "extraProperty": "Invalid"
      }
    },
    {
      "description": "llama-70b generated negative",
      "valid": false,
      "rust_error": "Additional properties are not allowed ('test' was unexpected)",
      "python_error": "Additional properties are not allowed ('test' was unexpected)\n\nFailed validating 'additionalProperties' in schema:\n    {'additionalProperties': False,\n     'description': 'Schema for an add-to-cart event',\n     'properties': {'category': {'type': 'string'},\n                    'currency': {'type': 'string'},\n                    'name': {'type': 'string'},\n                    'quantity': {'type': 'number'},\n                    'sku': {'type': 'string'},\n                    'unitPrice': {'type': 'number'}},\n     'required': ['sku', 'quantity'],\n     'self': {'format': 'jsonschema',\n              'name': 'add_to_cart',\n              'vendor': 'com.snowplowanalytics.snowplow',\n              'version': '1-0-0'},\n     'type': 'object'}\n\nOn instance:\n    {'category': 'Electronics',\n     'currency': 'USD',\n     'name': 'Apple iPhone 14',\n     'quantity': 1,\n     'sku': 'IPHONE14',\n     'unitPrice': 999.99,\n     'test': 'this is a test'}",
      "data": {
        "category": "Electronics",
        "currency": "USD",
        "name": "Apple iPhone 14",
        "quantity": 1,
        "sku": "IPHONE14",
        "unitPrice": 999.99,
        "test": "this is a test"
      }
    }
  ]
}